Workbook

Sheet Cover
B2: CLOZR BUSINESS SUITE
B3: UAT & System Test Checklist — Production Release Validation · v4 · Backend baseline: Clozr-Version02
B5: TEST RUN DETAILS
B6: Tester name | C6: Cijo George | E6: Browser & version | F6: e.g. Chrome 128
B7: Tester role | C7: Backend dev | E7: Device / OS | F7: windows
B8: Environment / URL | C8: Staging - dev.clozr.tech | E8: Test start (date & time) | F8: 46258
B9: App build / version | C9: release-2026-08-21 | E9: Test end (date & time) | F9: 46258.75
B11: RESULTS SUMMARY (fills in automatically as you mark each sheet)
B12: Module (sheet) | C12: Total | D12: Pass | E12: Fail | F12: Blocked | G12: Not Run | H12: % Passed
B13: 1. Onboarding & Login | C13: =COUNT('1. Onboarding & Login'!A2:A38) -> 31 | D13: =COUNTIF('1. Onboarding & Login'!D2:D38,"Pass") -> 0 | E13: =COUNTIF('1. Onboarding & Login'!D2:D38,"Fail") -> 0 | F13: =COUNTIF('1. Onboarding & Login'!D2:D38,"Blocked") -> 0 | G13: =C13-D13-E13-F13-COUNTIF('1. Onboarding & Login'!D2:D38,"N/A") -> 31 | H13: =IFERROR(D13/C13,0) -> 0
B14: 2. Admin - Users & Teams | C14: =COUNT('2. Admin - Users & Teams'!A2:A29) -> 23 | D14: =COUNTIF('2. Admin - Users & Teams'!D2:D29,"Pass") -> 0 | E14: =COUNTIF('2. Admin - Users & Teams'!D2:D29,"Fail") -> 0 | F14: =COUNTIF('2. Admin - Users & Teams'!D2:D29,"Blocked") -> 0 | G14: =C14-D14-E14-F14-COUNTIF('2. Admin - Users & Teams'!D2:D29,"N/A") -> 23 | H14: =IFERROR(D14/C14,0) -> 0
B15: 3. Roles & Scoping | C15: =COUNT('3. Roles & Scoping'!A2:A48) -> 37 | D15: =COUNTIF('3. Roles & Scoping'!D2:D48,"Pass") -> 0 | E15: =COUNTIF('3. Roles & Scoping'!D2:D48,"Fail") -> 0 | F15: =COUNTIF('3. Roles & Scoping'!D2:D48,"Blocked") -> 0 | G15: =C15-D15-E15-F15-COUNTIF('3. Roles & Scoping'!D2:D48,"N/A") -> 37 | H15: =IFERROR(D15/C15,0) -> 0
B16: 4. Editing & Audit Log | C16: =COUNT('4. Editing & Audit Log'!A2:A21) -> 16 | D16: =COUNTIF('4. Editing & Audit Log'!D2:D21,"Pass") -> 0 | E16: =COUNTIF('4. Editing & Audit Log'!D2:D21,"Fail") -> 0 | F16: =COUNTIF('4. Editing & Audit Log'!D2:D21,"Blocked") -> 0 | G16: =C16-D16-E16-F16-COUNTIF('4. Editing & Audit Log'!D2:D21,"N/A") -> 16 | H16: =IFERROR(D16/C16,0) -> 0
B17: 5. Filters, Columns & Views | C17: =COUNT('5. Filters, Columns & Views'!A2:A46) -> 37 | D17: =COUNTIF('5. Filters, Columns & Views'!D2:D46,"Pass") -> 0 | E17: =COUNTIF('5. Filters, Columns & Views'!D2:D46,"Fail") -> 0 | F17: =COUNTIF('5. Filters, Columns & Views'!D2:D46,"Blocked") -> 0 | G17: =C17-D17-E17-F17-COUNTIF('5. Filters, Columns & Views'!D2:D46,"N/A") -> 37 | H17: =IFERROR(D17/C17,0) -> 0
B18: 6. CRM - Leads | C18: =COUNT('6. CRM - Leads'!A2:A63) -> 52 | D18: =COUNTIF('6. CRM - Leads'!D2:D63,"Pass") -> 0 | E18: =COUNTIF('6. CRM - Leads'!D2:D63,"Fail") -> 0 | F18: =COUNTIF('6. CRM - Leads'!D2:D63,"Blocked") -> 0 | G18: =C18-D18-E18-F18-COUNTIF('6. CRM - Leads'!D2:D63,"N/A") -> 52 | H18: =IFERROR(D18/C18,0) -> 0
B19: 7. Capture & Routing | C19: =COUNT('7. Capture & Routing'!A2:A39) -> 33 | D19: =COUNTIF('7. Capture & Routing'!D2:D39,"Pass") -> 0 | E19: =COUNTIF('7. Capture & Routing'!D2:D39,"Fail") -> 0 | F19: =COUNTIF('7. Capture & Routing'!D2:D39,"Blocked") -> 0 | G19: =C19-D19-E19-F19-COUNTIF('7. Capture & Routing'!D2:D39,"N/A") -> 33 | H19: =IFERROR(D19/C19,0) -> 0
B20: 8. Money Path (Quote-Pay) | C20: =COUNT('8. Money Path (Quote-Pay)'!A2:A56) -> 42 | D20: =COUNTIF('8. Money Path (Quote-Pay)'!D2:D56,"Pass") -> 0 | E20: =COUNTIF('8. Money Path (Quote-Pay)'!D2:D56,"Fail") -> 0 | F20: =COUNTIF('8. Money Path (Quote-Pay)'!D2:D56,"Blocked") -> 0 | G20: =C20-D20-E20-F20-COUNTIF('8. Money Path (Quote-Pay)'!D2:D56,"N/A") -> 42 | H20: =IFERROR(D20/C20,0) -> 0
B21: 9. CRM - Records | C21: =COUNT('9. CRM - Records'!A2:A46) -> 37 | D21: =COUNTIF('9. CRM - Records'!D2:D46,"Pass") -> 0 | E21: =COUNTIF('9. CRM - Records'!D2:D46,"Fail") -> 0 | F21: =COUNTIF('9. CRM - Records'!D2:D46,"Blocked") -> 0 | G21: =C21-D21-E21-F21-COUNTIF('9. CRM - Records'!D2:D46,"N/A") -> 37 | H21: =IFERROR(D21/C21,0) -> 0
B22: 10. Project | C22: =COUNT('10. Project'!A2:A40) -> 31 | D22: =COUNTIF('10. Project'!D2:D40,"Pass") -> 17 | E22: =COUNTIF('10. Project'!D2:D40,"Fail") -> 5 | F22: =COUNTIF('10. Project'!D2:D40,"Blocked") -> 7 | G22: =C22-D22-E22-F22-COUNTIF('10. Project'!D2:D40,"N/A") -> 1 | H22: =IFERROR(D22/C22,0) -> 0.5483871
B23: 11. Helpdesk | C23: =COUNT('11. Helpdesk'!A2:A28) -> 22 | D23: =COUNTIF('11. Helpdesk'!D2:D28,"Pass") -> 10 | E23: =COUNTIF('11. Helpdesk'!D2:D28,"Fail") -> 2 | F23: =COUNTIF('11. Helpdesk'!D2:D28,"Blocked") -> 7 | G23: =C23-D23-E23-F23-COUNTIF('11. Helpdesk'!D2:D28,"N/A") -> 2 | H23: =IFERROR(D23/C23,0) -> 0.45454545
B24: 12. LMS (Training) | C24: =COUNT('12. LMS (Training)'!A2:A34) -> 26 | D24: =COUNTIF('12. LMS (Training)'!D2:D34,"Pass") -> 0 | E24: =COUNTIF('12. LMS (Training)'!D2:D34,"Fail") -> 0 | F24: =COUNTIF('12. LMS (Training)'!D2:D34,"Blocked") -> 0 | G24: =C24-D24-E24-F24-COUNTIF('12. LMS (Training)'!D2:D34,"N/A") -> 26 | H24: =IFERROR(D24/C24,0) -> 0
B25: 13. Automations | C25: =COUNT('13. Automations'!A2:A48) -> 38 | D25: =COUNTIF('13. Automations'!D2:D48,"Pass") -> 25 | E25: =COUNTIF('13. Automations'!D2:D48,"Fail") -> 2 | F25: =COUNTIF('13. Automations'!D2:D48,"Blocked") -> 3 | G25: =C25-D25-E25-F25-COUNTIF('13. Automations'!D2:D48,"N/A") -> 7 | H25: =IFERROR(D25/C25,0) -> 0.65789474
B26: 14. Goals & Rewards | C26: =COUNT('14. Goals & Rewards'!A2:A58) -> 45 | D26: =COUNTIF('14. Goals & Rewards'!D2:D58,"Pass") -> 7 | E26: =COUNTIF('14. Goals & Rewards'!D2:D58,"Fail") -> 0 | F26: =COUNTIF('14. Goals & Rewards'!D2:D58,"Blocked") -> 1 | G26: =C26-D26-E26-F26-COUNTIF('14. Goals & Rewards'!D2:D58,"N/A") -> 37 | H26: =IFERROR(D26/C26,0) -> 0.15555556
B27: 15. Billing | C27: =COUNT('15. Billing'!A2:A22) -> 17 | D27: =COUNTIF('15. Billing'!D2:D22,"Pass") -> 12 | E27: =COUNTIF('15. Billing'!D2:D22,"Fail") -> 3 | F27: =COUNTIF('15. Billing'!D2:D22,"Blocked") -> 1 | G27: =C27-D27-E27-F27-COUNTIF('15. Billing'!D2:D22,"N/A") -> 1 | H27: =IFERROR(D27/C27,0) -> 0.70588235
B28: 16. Communications | C28: =COUNT('16. Communications'!A2:A34) -> 27 | D28: =COUNTIF('16. Communications'!D2:D34,"Pass") -> 9 | E28: =COUNTIF('16. Communications'!D2:D34,"Fail") -> 1 | F28: =COUNTIF('16. Communications'!D2:D34,"Blocked") -> 10 | G28: =C28-D28-E28-F28-COUNTIF('16. Communications'!D2:D34,"N/A") -> 6 | H28: =IFERROR(D28/C28,0) -> 0.33333333
B29: 17. Reports | C29: =COUNT('17. Reports'!A2:A18) -> 14 | D29: =COUNTIF('17. Reports'!D2:D18,"Pass") -> 5 | E29: =COUNTIF('17. Reports'!D2:D18,"Fail") -> 2 | F29: =COUNTIF('17. Reports'!D2:D18,"Blocked") -> 4 | G29: =C29-D29-E29-F29-COUNTIF('17. Reports'!D2:D18,"N/A") -> 3 | H29: =IFERROR(D29/C29,0) -> 0.35714286
B30: 18. Misc (Cross-Module) | C30: =COUNT('18. Misc (Cross-Module)'!A2:A52) -> 38 | D30: =COUNTIF('18. Misc (Cross-Module)'!D2:D52,"Pass") -> 0 | E30: =COUNTIF('18. Misc (Cross-Module)'!D2:D52,"Fail") -> 0 | F30: =COUNTIF('18. Misc (Cross-Module)'!D2:D52,"Blocked") -> 0 | G30: =C30-D30-E30-F30-COUNTIF('18. Misc (Cross-Module)'!D2:D52,"N/A") -> 38 | H30: =IFERROR(D30/C30,0) -> 0
B31: GRAND TOTAL | C31: =SUM(C13:C30) -> 566 | D31: =SUM(D13:D30) -> 85 | E31: =SUM(E13:E30) -> 15 | F31: =SUM(F13:F30) -> 33 | G31: =SUM(G13:G30) -> 429 | H31: =IFERROR(D31/C31,0) -> 0.15017668
B33: Overall release verdict | C33: Go / No-Go
B34: Signed off by / date
B36: Notes / blockers:

Sheet How to Use
B2: How to use this checklist
B3: This workbook checks that every part of the Clozr Business Suite works before it goes live. You do not need any technical knowledge. Just do what each row says and mark what happened.
B4: The tabs at the bottom
B5: • Cover — fill in your name and details at the top. The results table fills in by itself as you work.
B6: • How to Use — this page.
B7: • One tab per area of the app (Onboarding, Admin, CRM, Project, Helpdesk, LMS, Billing, Communications, Reports). The last tab, 'Misc', covers things that affect the whole app.
B8: Each test row has five columns
B9: • Sl No — the row number.
B10: • Action — what YOU should do in the app.
B11: • Expected Outcome — what SHOULD happen if the app is working correctly.
B12: • Result — click the cell and pick Pass, Fail, Blocked or N/A from the drop-down.
B13: • Remarks — write anything you noticed: what went wrong, a screenshot name, or a question.
... B38: • You should never see a raw technical error, a blank white page, or a loader that never stops. If you do, note it as a Fail with the screen name.

Sheet 1. Onboarding & Login
A1: Sl No | B1: Action | C1: Expected Outcome | D1: Result | E1: Remarks
A2: A. SIGN UP A NEW COMPANY (WORKSPACE)
A3: 1 | B3: Open the sign-up page and register a new company with a valid name, a web address (subdomain), your name, e-mail and a strong password. | C3: The company is created. You are told to check your e-mail, or you are taken into the app.
A4: 2 | B4: Try to sign up again using the SAME company web address (subdomain). | C4: Blocked with a clear 'web address already taken' message.
A5: 3 | B5: Try to sign up with the SAME company name as an existing company. | C5: Blocked with a clear 'company name already exists' message.
A6: 4 | B6: Try to sign up with a badly-formed e-mail such as 'john@' or 'john.com'. | C6: Blocked; e-mail marked not valid. The company is NOT created.
A7: 5 | B7: Try to sign up with a very weak password such as '123'. | C7: Blocked; the password rules are shown (length, letters, numbers, special sign).
A8: 6 | B8: Leave the company name blank and press Sign up. | C8: Blocked; company name marked as required.
A9: 7 | B9: Type a company name of about 300 letters and sign up. | C9: The app trims sensibly or shows a clear limit message; it does not crash or show a raw error.
A10: 8 | B10: Paste <script>alert(1)</script> into the company name and sign up. | C10: The text is stored as plain words; no pop-up ever appears where the name is later shown.
A11: B. ACTIVATE THE ACCOUNT (E-MAIL LINK)
A12: 9 | B12: Open the activation e-mail, click the link and set a password. | C12: The password is accepted and the account becomes active.
A13: 10 | B13: Click the SAME activation link again after the account is already active. | C13: Handled gracefully with a clear message; no broken page or raw error.
A14: 11 | B14: Wait until the activation link is expired, click it, then use 'resend activation'. | C14: The old link is refused; a fresh activation e-mail is sent.
A15: C. LOG IN
A16: 12 | B16: Log in with the correct e-mail and password. | C16: Signed in; you land on the Dashboard.
A17: 13 | B17: Log in with the correct e-mail but a WRONG password. | C17: Refused with a clear message that does NOT reveal whether the e-mail exists.
A18: 14 | B18: Leave both e-mail and password blank and press Log in. | C18: Both boxes marked required; no login attempt is made.
A19: 15 | B19: Enter a wrong password 5 times in a row for the same e-mail. | C19: After the set number of tries the account is locked with a clear message.
A20: 16 | B20: While locked, try to log in with the CORRECT password. | C20: Still refused because the account is locked.
A21: 17 | B21: Wait for the lock time to pass (or ask admin to reset), then log in correctly. | C21: Login works again.
A22: 18 | B22: After being locked and then logging in once correctly, fail again and count the tries. | C22: The failed-attempt count was reset by the good login; a fresh set of tries is allowed.
A23: D. TWO-STEP LOGIN (2FA) — IF TURNED ON
A24: 19 | B24: Turn on two-step login in security settings and complete setup. | C24: Two-step login is set up and confirmed.
A25: 20 | B25: Log out and log in again with two-step login on. | C25: After the password, the app asks for the second code before letting you in.
A26: 21 | B26: On the second-step screen, type a wrong code. | C26: The code is refused; you are not let in.
A27: 22 | B27: Turn off two-step login. | C27: The next login needs only the password.
A28: E. STAYING LOGGED IN / SESSIONS
A29: 23 | B29: Stay active for more than 30 minutes without logging out. | C29: You are not thrown out mid-work; the session stays alive quietly.
A30: 24 | B30: Leave the app idle for the inactivity period set in security policy, then return. | C30: The app behaves per the inactivity rule; it does not silently keep an unsafe session.
A31: 25 | B31: Open Settings > Security > Sessions. | C31: Your current sign-in is listed with device/browser and last-active time.
A32: 26 | B32: Log in from a second browser/device with the same account. | C32: The second session appears; both work per the max-sessions rule (default 5).
A33: 27 | B33: Click Log out, then press browser Back and try to reach an inside page. | C33: You are sent to the login page, not shown old page content.
A34: F. FORGOT PASSWORD
A35: 28 | B35: Use 'Forgot password', enter your e-mail and submit. | C35: You are told a reset link has been sent (whether or not the e-mail exists).
A36: 29 | B36: Open the reset e-mail, click the link and set a new password. | C36: The new password is accepted; you can log in with it.
A37: 30 | B37: Try the same reset link again, or after it has expired. | C37: Refused with a clear message; it cannot be reused.
A38: 31 | B38: Request a reset for an e-mail that does NOT exist. | C38: The same neutral 'link sent' message appears; it does not reveal the e-mail is unknown.

Sheet 2. Admin - Users & Teams
A1: Sl No | B1: Action | C1: Expected Outcome | D1: Result | E1: Remarks
A2: A. COMPANY PROFILE & BRANDING
A3: 1 | B3: Fill in the company profile: logo, brand colours, address, time zone, date format, first day of week, currency. | C3: All values save and show correctly on re-open.
A4: 2 | B4: Change the company currency (INR / USD / EUR / AED) and save. | C4: The new currency is used where money is shown for new records.
A5: 3 | B5: Set business hours and turn on 'restrict to business hours'. | C5: The setting saves (it later affects lead auto-assignment timing).
A6: 4 | B6: Upload a company logo larger than 10 MB. | C6: Refused with a clear size message; no hang or crash.
A7: 5 | B7: Upload a non-image file renamed to .png as the logo. | C7: Rejected as an invalid image with a clear message.
A8: 6 | B8: Set the financial year start month and first day of week, then open a dashboard with a date range. | C8: Date ranges and week grouping follow the company settings.
A9: B. INVITE & MANAGE USERS
A10: 7 | B10: Add a new user with name, e-mail and role. | C10: The user is created and an activation e-mail is sent.
A11: 8 | B11: Try to add a user with an e-mail ALREADY used by any user in the system. | C11: Blocked; e-mail already in use.
A12: 9 | B12: Open the new user's detail page. | C12: It shows the user's information, role and status.
A13: 10 | B13: Deactivate a user, then try to log in as them. | C13: Login is refused; the user is inactive.
A14: 11 | B14: Re-activate the user and log in. | C14: The user can log in once active.
A15: 12 | B15: Mark a user as non-billable (service account) if available. | C15: Saved as non-billable; does not add to the paid seat count.
A16: 13 | B16: Deactivate a user who OWNS leads and customers, then look at those records. | C16: The records are not deleted; ownership is cleared or handled cleanly, not broken.
A17: C. TEAMS
A18: 14 | B18: Create a team with a manager and several members. | C18: The team saves with its manager and members.
A19: 15 | B19: Try to create a second team with the SAME name. | C19: Blocked; team name already exists.
A20: 16 | B20: Remove a member from a team and add a different one. | C20: Membership updates correctly.
A21: 17 | B21: Assign a lead to a TEAM (not a person). | C21: The lead shows the assigned team.
A22: D. REPORTING HIERARCHY
A23: 18 | B23: Set a manager for a user from the hierarchy screen. | C23: Saved and shown in the hierarchy tree.
A24: 19 | B24: Open the hierarchy tree view. | C24: The tree shows who reports to whom.
A25: 20 | B25: Try to give a user two active managers at the same time. | C25: The app keeps only one active manager; the old one is replaced cleanly.
A26: 21 | B26: Build a chain: A manages B, B manages C. View subordinates for A. | C26: A's subordinates include BOTH B and C (the whole chain, not just direct reports).
A27: E. AUDIT TRAIL
A28: 22 | B28: Create a lead, edit a user and change a role, then open the Audit Log. | C28: The three actions appear with who did them and when.
A29: 23 | B29: Export the audit log (if your role allows). | C29: A file downloads with the audit entries.

Sheet 3. Roles & Scoping
A1: Sl No | B1: Action | C1: Expected Outcome | D1: Result | E1: Remarks
A2: A. BUILD ROLES (module permissions = WHAT you can do)
A3: 1 | B3: Create a role and turn ON only View and Export for Leads (Create/Edit/Delete/Import/Approve OFF). | C3: The choices save exactly as set.
A4: 2 | B4: Assign that role to test user U1, log in as U1 and open Leads. | C4: U1 can see and export leads, but Add / Edit / Delete are hidden or blocked.
A5: 3 | B5: As U1, open the New Lead page by typing its web address directly. | C5: Blocked with a clear 'no access' message (server-enforced, not just a hidden button).
A6: 4 | B6: As U1, find the delete action's address and try to trigger a delete directly. | C6: The delete is refused on the server too, not only hidden in the screen.
A7: 5 | B7: Turn ON Import for Leads for U1's role and reload; try to import. | C7: Import is now allowed for U1.
A8: 6 | B8: Give a role Approve on Leads but NOT Edit; check lead conversion approval. | C8: The Approve permission works for approvals even though Edit is off.
A9: 7 | B9: Create a user with NO role and log in. | C9: They see almost no menu items and cannot open the gated screens.
A10: B. SCOPE = OWNED (which records you can see)
A11: 8 | B11: SETUP: Create role 'Owned-Only' with Lead visibility = Owned records. Assign to U2, who is NOT in any team. Create Lead-A owned by U2 and Lead-B owned by someone else. Log in as U2. | C11: Setup ready.
A12: 9 | B12: As U2, open the Leads list. | C12: U2 sees Lead-A (their own) but NOT Lead-B.
A13: 10 | B13: As U2, open Lead-B directly by its web address. | C13: Blocked — U2 cannot open a lead they do not own.
A14: 11 | B14: As U2, edit Lead-A. | C14: Allowed — the owner can always edit their own record.
A15: 12 | B15: Assign Lead-B to U2 as an ASSIGNEE (keep a different owner). As U2, open the list. | C15: Lead-B now also appears for U2 — 'owned' scope also includes records assigned to the user.
A16: C. SCOPE = OWNED + TEAM OVERLAY (important hidden behaviour)
A17: 13 | B17: SETUP: Put U2 into a Team with teammate U3. U3 owns Lead-C. Keep U2's role at 'Owned records'. Log in as U2. | C17: Setup ready.
A18: 14 | B18: As U2 (owned scope) open the Leads list and look for U3's Lead-C. | C18: Lead-C IS visible to U2 — being on a team quietly adds teammates' records even under 'owned' scope. Confirm this is intended.
A19: 15 | B19: Remove U2 from the team and reload the list (allow a few minutes for permissions to refresh). | C19: Lead-C disappears for U2 once they are no longer a teammate.
A20: D. SCOPE = ASSIGNED / TEAM / HIERARCHY / ALL
A21: 16 | B21: SETUP: Create role 'Assigned-Only' (Lead = Assigned records), assign to U4 not in a team. Make U4 an assignee on Lead-D only. Log in as U4. | C21: Setup ready.
A22: 17 | B22: As U4 open the Leads list. | C22: U4 sees only leads they are an assignee on (Lead-D), not ones merely owned by others.
A23: 18 | B23: SETUP: Create role 'Team-Scope' (Lead = Team records), assign to U5 who shares a team with U6. U6 owns Lead-E. Log in as U5. | C23: Setup ready.
A24: 19 | B24: As U5 open the Leads list. | C24: U5 sees leads owned/assigned by any teammate (including U6's Lead-E).
A25: 20 | B25: SETUP: Create role 'Hierarchy-Scope' (Lead = Hierarchy records) for manager M who manages S1 who manages S2. Log in as M. | C25: Setup ready.
A26: 21 | B26: As M open the Leads list with M, S1 and S2 each owning a lead. | C26: M sees M's, S1's AND S2's leads (own + everyone below, all the way down).
A27: 22 | B27: SETUP: Create role 'All-Scope' (Lead = All records) for U7. Log in as U7. | C27: Setup ready.
A28: 23 | B28: As U7 open the Leads list. | C28: U7 sees every lead in the company.
A29: E. SCOPE = FILTERED (custom condition)
A30: 24 | B30: SETUP: Create role 'Filtered' with Lead = Filtered records and a condition (e.g. only a chosen source or territory). Assign to U8. Create leads matching and not matching the condition. | C30: Setup ready.
A31: 25 | B31: As U8 open the Leads list. | C31: U8 sees only the leads that match the saved filter condition, and no others.
A32: F. WHEN A USER HAS TWO ROLES (precedence)
A33: 26 | B33: Give one user BOTH an 'Owned records' role and an 'All records' role for Leads. Log in as them. | C33: The wider scope wins — they see ALL leads (precedence order: All > Hierarchy > Team > Owned > Assigned > Filtered).
A34: 27 | B34: Give a user a 'Team' role and a 'Hierarchy' role for Leads. | C34: The Hierarchy scope wins over Team (higher precedence).
A35: G. EDIT vs VIEW at record level
A36: 28 | B36: Give U9 'View = All' but 'Edit = Owned' for Leads. As U9 open a lead they do NOT own and try to edit it. | C36: U9 can open/read it but cannot save changes to a lead they do not own.
A37: 29 | B37: As that same U9, edit a lead they DO own. | C37: Allowed.
A38: H. RECORD SHARING (one-off, with expiry)
A39: 30 | B39: Share a single lead with a colleague and set an expiry a few minutes ahead. | C39: The colleague can open that one lead now.
A40: 31 | B40: After the expiry passes, the colleague opens the shared lead again. | C40: Access is gone; it can no longer be opened.
A41: 32 | B41: Share a lead with 'view' only (not edit) and have the colleague try to edit it. | C41: They can view but not edit the shared lead.
A42: I. PERSONAL DATA FILTERS (narrow a single user)
A43: 33 | B43: Add an 'exclude' data filter for a user on a field (e.g. exclude a region). As that user open the list. | C43: Records in the excluded region are hidden from that user, on top of their role scope.
A44: 34 | B44: Add an 'include' data filter (e.g. only one product). As that user open the list. | C44: Only records matching the include filter are shown.
A45: J. ADMIN BYPASS & SCOPE ACROSS MODULES
A46: 35 | B46: Log in as a System Admin (staff) and open Leads, Customers, Projects. | C46: The admin sees everything with no scope limits.
A47: 36 | B47: Repeat the 'Owned records' scope test on CUSTOMERS and on TASKS (not just Leads). | C47: The same scope rule applies consistently across modules, not only for leads.
A48: 37 | B48: Change a user's role, then have them keep using the app WITHOUT reloading for a few minutes. | C48: The change may take up to ~5 minutes or a reload to take effect (permissions are cached). Confirm it does apply after that.

Sheet 4. Editing & Audit Log
A1: Sl No | B1: Action | C1: Expected Outcome | D1: Result | E1: Remarks
A2: A. EDITS PERSIST AND ARE AUDITED (do this for each record type below)
A3: 1 | B3: Edit an existing LEAD: change its name, owner and one custom field; save. | C3: The changes are saved and still show after you reload the lead.
A4: 2 | B4: Open Admin > Audit Log and find that lead edit. | C4: There is an 'update' entry naming WHO edited it and WHEN, and showing the before and after values.
A5: 3 | B5: Edit an existing CUSTOMER (e.g. status, SLA) and check the audit log. | C5: The change persists and an 'update' entry with before/after is recorded.
A6: 4 | B6: Edit a PRODUCT (e.g. price) and check the audit log. | C6: The change persists and is recorded with before/after.
A7: 5 | B7: Edit a PROJECT TASK (e.g. status, assignees) and check the audit log. | C7: The change persists and is recorded.
A8: 6 | B8: Edit a HELPDESK TICKET (e.g. priority, status) and check the audit log. | C8: The change persists and is recorded.
A9: 7 | B9: Edit a QUOTATION (e.g. a line item, notes) and check the audit log. | C9: The change persists and is recorded (unless money is locked — see Money Path).
A10: 8 | B10: Edit a USER and a ROLE (e.g. rename, change permissions) and check the audit log. | C10: Both changes persist and are recorded, including permission changes.
A11: B. CREATE & DELETE ARE AUDITED
A12: 9 | B12: Create a brand-new record (e.g. a lead) and check the audit log. | C12: A 'create' entry is recorded for it.
A13: 10 | B13: Delete a record (e.g. a task) and check the audit log. | C13: A 'delete' entry is recorded for it.
A14: 11 | B14: Do a BULK action (e.g. bulk status change on several leads) and check the audit log. | C14: The bulk change is recorded.
A15: C. WHAT IS AND IS NOT CAPTURED
A16: 12 | B16: Just OPEN/VIEW a record without changing anything, then check the audit log. | C16: Simply viewing is NOT logged — only creates, edits and deletes are.
A17: 13 | B17: Edit a record that contains a secret/password field (e.g. an integration setting) and open its audit entry. | C17: Any secret value is masked in the audit entry, not shown in clear text.
A18: 14 | B18: Log in and log out, then check the audit log. | C18: Login and logout are recorded as security events.
A19: D. AUDIT ACCESS & EXPORT
A20: 15 | B20: As a user WITHOUT audit permission, try to open the Audit Log. | C20: Access is blocked or the menu item is hidden.
A21: 16 | B21: As a permitted user, filter the audit log (by user, by action, by date) and export it. | C21: Filtering works and an export file downloads.

Sheet 5. Filters, Columns & Views
A1: Sl No | B1: Action | C1: Expected Outcome | D1: Result | E1: Remarks
A2: A. CREATE CUSTOM FIELDS (leads)
A3: 1 | B3: Create a custom lead field of type Text; another Number; another Date; another Checkbox (yes/no); another Dropdown with a few choices. | C3: Each field type saves and appears on the lead form.
A4: 2 | B4: Mark the Dropdown field as REQUIRED, then create a lead and leave it blank. | C4: Saving is blocked until the required field has a value.
A5: 3 | B5: On that Dropdown field, type a value that is NOT one of its choices (if possible) and save. | C5: Blocked with a message like 'must be one of: ...'.
A6: 4 | B6: In the Number custom field, type letters. In the Date custom field, type an impossible date. | C6: Bad values are blocked with clear messages; no broken data is saved.
A7: 5 | B7: Set the display ORDER of custom fields and reopen the lead form. | C7: The fields appear in the set order.
A8: 6 | B8: Try to create two custom fields with the same name/key. | C8: Blocked; the field key must be unique for that record type.
A9: 7 | B9: Turn a custom field to inactive. | C9: It stops appearing on the form for new entries.
A10: B. CUSTOM FIELDS IN LISTS, FILTERS, IMPORT/EXPORT
A11: 8 | B11: Turn ON 'show in list' for a custom field, then open the Leads list. | C11: The custom field appears as a column you can show.
A12: 9 | B12: Filter or sort the Leads list by a custom field. | C12: The list filters/sorts by the custom field value.
A13: 10 | B13: Export leads that have custom field values. | C13: The exported file includes the custom field columns and values.
A14: 11 | B14: Import leads from a file that includes a custom field column. | C14: The custom values are imported onto the leads; bad values are reported.
A15: C. CUSTOM FIELDS FLOWING INTO RULES (cross-feature)
A16: 12 | B16: Create a routing rule that uses a custom field as a condition, then create a matching lead. | C16: The lead is routed based on the custom field value.
A17: 13 | B17: Create an automation rule that reads a custom field, then DELETE that custom field. | C17: The automation is marked invalid / warned (it points to a removed field), rather than silently misbehaving. (If automations are not available, mark N/A and note it.)
A18: D. CUSTOM FIELDS ON OTHER RECORDS
A19: 14 | B19: If the app allows custom fields on records other than leads (e.g. contacts, products), create one and use it. | C19: The custom field works on that record the same way. If not available for that record, mark N/A.
A20: 15 | B20: For Products, create a product extension schema with fields and attach it to a product. | C20: The product carries the extra fields and validates them.
A21: E. PERSONAL VIEW SETTINGS (columns, sort, filters)
A22: 16 | B22: On the Leads list, change which columns are shown and their order; change the sort; save the view. | C22: Your column choice, order and sort are remembered for you after reload.
A23: 17 | B23: Log in as a DIFFERENT user and open the same Leads list. | C23: The other user sees their OWN view (or the company default), not your personal changes.
A24: 18 | B24: Set a company DEFAULT view for leads (as admin), then have a user who has not customised anything open the list. | C24: That user sees the company default view.
A25: 19 | B25: Customise a user's own view, then confirm the source shown is 'custom' vs 'default' for a fresh user. | C25: A customised user is on their own view; an untouched user falls back to the default.
A26: 20 | B26: Repeat view settings on another record type (e.g. Products or Contacts). | C26: View settings work per record type and per view (list/detail/form), independently.
A27: 21 | B27: Ask for a saved view with an invalid record type or view type (edge input). | C27: The app rejects it with a clear message listing the valid choices.
A28: F. SAVED FILTERS
A29: 22 | B29: On the Leads list, apply a few filters and Save them as a named filter. | C29: The saved filter appears as a chip/entry you can re-apply.
A30: 23 | B30: Click the saved filter later. | C30: The list re-applies exactly those filter conditions.
A31: 24 | B31: Try to save a filter with the SAME name as an existing one for the same list. | C31: Blocked with a clear 'a filter with that name already exists' message.
A32: 25 | B32: Try to Save a filter with NO conditions set. | C32: Blocked; you are asked to add at least one filter first.
A33: 26 | B33: Save filters until you reach the limit (5 per list), then try to save a 6th. | C33: The 6th is blocked with a clear 'limit of 5 reached' message.
A34: 27 | B34: Build a filter on a field, then have an admin remove/rename that field; re-open the saved filter. | C34: The saved filter is shown as invalid/needs attention rather than silently filtering wrongly.
A35: 28 | B35: Edit an existing saved filter's conditions and save. | C35: The edit is saved and re-applying uses the new conditions (editing in place is not blocked by the limit).
A36: 29 | B36: Log in as a DIFFERENT user and look for your saved filter. | C36: Saved filters are private to each user — the other user does not see yours.
A37: 30 | B37: Delete a saved filter. | C37: It is removed from your list.
A38: G. DEFAULT / SYSTEM FILTERS
A39: 31 | B39: Open a list and look at the built-in quick filters/tabs (e.g. All / My / Unassigned). | C39: The default system filters work and show the right subset.
A40: 32 | B40: Open a list fresh (no filter chosen). | C40: The list opens on its sensible default view, not an error or a random subset.
A41: H. CUSTOM COLUMNS & RE-ARRANGING
A42: 33 | B42: Open a list and turn some columns ON and others OFF (including a custom field column). | C42: The chosen columns show/hide immediately.
A43: 34 | B43: Drag to RE-ORDER the columns into a new order. | C43: The columns move to the new order.
A44: 35 | B44: Reload the page. | C44: Your column choice and order are remembered for you.
A45: 36 | B45: Reset the columns to default (if available). | C45: The list returns to the default column set.
A46: 37 | B46: Have an admin set a company DEFAULT column layout, then a brand-new user opens the list. | C46: The new user sees the company default layout until they customise their own.

Sheet 6. CRM - Leads
A1: Sl No | B1: Action | C1: Expected Outcome | D1: Result | E1: Remarks
A2: A. SET UP LEAD PIPELINE
A3: 1 | B3: Create lead stages (e.g. New, Qualified, Won, Lost) each with a colour and order. | C3: Stages save with colours and order.
A4: 2 | B4: Mark one stage default, one 'converted/won', one 'lost'. Try to set a SECOND default. | C4: Only one of each is allowed; the second default is blocked.
A5: 3 | B5: Try to delete a stage that leads are using. | C5: Blocked; the stage is in use.
A6: 4 | B6: Create lead sources, lost reasons and a hierarchical territory (a zone with a sub-zone). | C6: They save and are available on the lead form.
A7: B. CREATE LEADS
A8: 5 | B8: Create a lead with full details: name, company, e-mail, phone with country code, source, owner. | C8: Saved and opens with all details correct.
A9: 6 | B9: Create a lead with only a first name. | C9: Saved; the full name is built from the first name.
A10: 7 | B10: Create a lead with NO first name at all. | C10: Saved; it gets an auto number like LEAD-00001.
A11: 8 | B11: Create many auto-named leads quickly (or two at the exact same moment). | C11: Each gets a unique number; no two leads share the same auto number.
A12: 9 | B12: Create two leads with the exact same full name. | C12: Blocked; lead names are unique within the company.
A13: 10 | B13: Enter an e-mail without '@' and a phone with letters. | C13: Bad contact values are blocked or cleaned; obviously broken details are not saved silently.
A14: 11 | B14: Type a very long description (thousands of characters) and add emoji and non-English letters. | C14: Saved and shown correctly without breaking the layout.
A15: 12 | B15: Set the 'unsubscribed' and 'do-not-disturb' flags on a lead. | C15: The flags save (outbound tools should later respect them).
A16: C. DUPLICATE DETECTION
A17: 13 | B17: Turn on duplicate detection by e-mail, then create a lead with the same e-mail as an existing one. | C17: The new lead is flagged as a possible duplicate; not silently merged or deleted.
A18: 14 | B18: Switch duplicate detection to 'phone' and repeat with a matching phone. | C18: The duplicate is detected by phone.
A19: 15 | B19: Switch to 'both' and create a lead matching only e-mail, then only phone. | C19: Either match flags a duplicate.
A20: D. LEAD SCORING (0-100)
A21: 16 | B21: Open a lead and view its score and the score breakdown. | C21: A score 0-100 with a simple breakdown is shown.
A22: 17 | B22: Add several activities/interactions to a lead, then recalculate scores. | C22: The score rises to reflect recent activity and interaction count.
A23: 18 | B23: Compare a lead touched today vs one untouched for 2 months after recalculation. | C23: The recently-touched lead scores higher (recency and consistency both reward recent activity).
A24: 19 | B24: Select many leads and use 'Recalculate scores'. | C24: All selected scores update.
A25: E. LISTS & BULK ACTIONS
A26: 20 | B26: Filter by stage, owner and source; sort by a column; search by name. | C26: The list updates correctly for each.
A27: 21 | B27: Select several leads and Bulk Assign to another owner. | C27: All move to the new owner.
A28: 22 | B28: Select several leads and Bulk Change Status. | C28: All change to the new stage.
A29: 23 | B29: Select several leads and Bulk Delete. | C29: They are removed (recoverable if soft-deleted).
A30: 24 | B30: Bulk archive lost leads (turn on auto-archive lost leads and mark some lost). | C30: Lost leads are archived as configured.
A31: 25 | B31: Select zero leads and press a bulk action. | C31: The app does nothing harmful and prompts you to select rows.
A32: 26 | B32: Page through a very large leads list. | C32: Paging is smooth (100 per page); no freeze or loading everything at once.
A33: F. CONVERSION APPROVAL (deep — see Money Path for the money side)
A34: 27 | B34: As a salesperson, raise a conversion approval request with a reason. | C34: A pending request is created.
A35: 28 | B35: As the SAME salesperson, try to approve your own request. | C35: Blocked; you cannot approve your own.
A36: 29 | B36: As a peer at the same level (not the manager), try to approve. | C36: Blocked; the approver must be above the requester in the chain.
A37: 30 | B37: As the requester's manager (or higher up the chain), approve it. | C37: Approved; the lead may convert.
A38: 31 | B38: As a grand-manager two levels up, approve a request. | C38: Approved — the whole management chain can approve, not only the direct manager.
A39: 32 | B39: Raise a second approval request for the same lead while one is pending. | C39: Blocked; only one pending request per lead.
A40: 33 | B40: Give the approver the Approve permission but remove it, then try to approve. | C40: Without Approve permission the approval is refused even for a manager.
A41: G. HIERARCHICAL TERRITORY (zone -> sub-zone)
A42: 34 | B42: Create a top territory (zone), then create a sub-zone under it, then a sub-sub-zone. | C42: The territory tree is built with parent/child levels.
A43: 35 | B43: Assign a lead to a sub-zone. | C43: The lead shows the sub-zone; territory-based views/routing can use it.
A44: 36 | B44: Move a sub-zone under a different parent zone. | C44: The tree updates; the moved branch keeps its own children.
A45: 37 | B45: Try to delete a territory that leads are using. | C45: Blocked with a clear message that it is referenced by existing leads.
A46: 38 | B46: Delete an unused sub-zone. | C46: It is removed cleanly.
A47: H. UNSUBSCRIBE & DO-NOT-DISTURB FLAGS
A48: 39 | B48: Open a lead and turn ON 'unsubscribed', then try to send that lead a WhatsApp message. | C48: The send is BLOCKED with a clear 'recipient has unsubscribed' message.
A49: 40 | B49: Turn ON 'do not disturb' on a lead and try to contact them through each channel (call, WhatsApp, email). | C49: Each outbound channel respects the flag. NOTE whether e-mail sending also blocks/warns — if it does NOT, record it as a finding.
A50: 41 | B50: Turn the flags back OFF and retry a message. | C50: Sending works again once the flags are cleared.
A51: I. DUPLICATE RULES — KEYS, SCOPE & ON-MATCH
A52: 42 | B52: Open lead rules and set the duplicate MATCH KEYS (e.g. e-mail; then e-mail + phone). | C52: The chosen match keys save.
A53: 43 | B53: Set the CHECK SCOPE to 'customers only', then create a lead matching an existing CUSTOMER. | C53: The match is found against customers per the scope.
A54: 44 | B54: Set the scope to 'leads and customers' and create a lead matching an existing LEAD. | C54: The match is found against leads too.
A55: 45 | B55: Set ON-MATCH to 'warn' and create a matching lead. | C55: The lead is still created but a duplicate WARNING is shown listing the matches.
A56: 46 | B56: Set ON-MATCH to 'block' and create a matching lead. | C56: Creation is BLOCKED because a duplicate exists.
A57: 47 | B57: Set ON-MATCH to 'merge' and create a matching lead (if merge is offered). | C57: The new details merge into the existing record instead of making a second one.
A58: 48 | B58: Convert a lead whose details match an existing customer. | C58: The resulting customer is flagged as a possible duplicate.
A59: J. LEAD SCORE — BREAKDOWN DETAIL
A60: 49 | B60: Open a lead's score breakdown and read each part (recency, interactions, deal value, consistency, conversion). | C60: Each part shows its own points and a short reason.
A61: 50 | B61: Add up the parts and compare to the total score. | C61: The parts add up to the total shown (0-100).
A62: 51 | B62: Check the supporting numbers in the breakdown (e.g. interaction count in last 90 days, deal value used). | C62: The numbers match the lead's real activity and its highest quotation/revenue/product value.
A63: 52 | B63: Change something that should raise the score (add a recent activity, attach a bigger quotation) and recalculate. | C63: The relevant part of the breakdown and the total go up accordingly.

Sheet 7. Capture & Routing
A1: Sl No | B1: Action | C1: Expected Outcome | D1: Result | E1: Remarks
A2: A. WEBSITE LEAD CAPTURE (WEBHOOK KEY)
A3: 1 | B3: Create a website capture key with a source, default owner and default stage. | C3: Created; only the last 4 characters of the secret are shown.
A4: 2 | B4: Set 'browser mode' with an allowed website address and submit a test lead from that address. | C4: The lead is captured and appears in the leads list with the default source/owner/stage.
A5: 3 | B5: Submit from a website address NOT on the allowed list. | C5: Rejected.
A6: 4 | B6: Set 'signed/server mode' and submit WITHOUT the correct signature. | C6: Rejected.
A7: 5 | B7: Submit the signed lead WITH the correct signature. | C7: Captured successfully.
A8: 6 | B8: Send more submissions per minute than the key's limit (default 30). | C8: Extra submissions that minute are rejected.
A9: 7 | B9: Deactivate or revoke the key and submit again. | C9: Refused because the key is off.
A10: 8 | B10: Open the capture history/log. | C10: Each attempt is listed as Accepted, Rejected or Duplicate with details.
A11: 9 | B11: Submit a lead with missing or junk fields. | C11: Handled gracefully — captures what it can or rejects with a clear log entry; no crash.
A12: 10 | B12: Submit a lead that duplicates an existing one (with duplicate detection on). | C12: It is logged as Duplicate and flagged.
A13: B. META (FACEBOOK / INSTAGRAM) LEAD ADS
A14: 11 | B14: Connect a Meta advertising account (app id, token, page) in Meta Ads settings. | C14: The connection saves and shows connected.
A15: 12 | B15: Pull leads from Meta (bulk pull) and view the staged leads. | C15: Meta leads appear in a staging list, not straight in the pipeline.
A16: 13 | B16: Promote staged Meta leads into real leads. | C16: The promoted leads appear in the normal leads list.
A17: 14 | B17: Enter a wrong token or disconnect, then pull leads. | C17: A clear connection error is shown, not a broken page.
A18: C. AUTOMATIC ROUTING (assignment rules)
A19: 15 | B19: Create a routing rule with conditions (e.g. source = Meta) and a target team, with points. | C19: The rule saves.
A20: 16 | B20: Try to save a rule with NO target team and NO target role. | C20: Blocked; a team or role is required.
A21: 17 | B21: Try to save a rule with EMPTY conditions. | C21: Blocked; conditions are required.
A22: 18 | B22: Create a lead matching the rule and check who it is assigned to. | C22: Auto-assigned to an eligible person from the matching rule.
A23: 19 | B23: Create two rules with different priorities that both match a lead. | C23: Rules are applied in priority order (lower number first); points add up as designed.
A24: 20 | B24: Create a lead that matches NO rule. | C24: The lead is left with a clear 'no match' state, not lost.
A25: 21 | B25: Turn on 'restrict to business hours' and create a lead OUTSIDE business hours. | C25: Assignment is held as 'pending' and happens when business hours resume.
A26: 22 | B26: Set two agents with equal points and send matching leads. | C26: Leads are shared fairly — fewest open leads first, then longest wait.
A27: D. ROUTING — DEEPER CORNER CASES
A28: 23 | B28: Create three rules with different priorities and overlapping conditions; create a lead matching all three. | C28: Rules apply in priority order (lower number first) and points accumulate as designed; the winner is the agent with the most points.
A29: 24 | B29: Two eligible agents end with equal points; one has fewer open leads. | C29: The agent with fewer open leads wins the tie.
A30: 25 | B30: Two eligible agents have equal points AND equal open-lead counts. | C30: The agent who has waited longest since their last lead wins (round-robin).
A31: 26 | B31: Disable a routing rule, then create a lead that only that rule matched. | C31: The disabled rule is ignored; the lead falls through to the next rule or to 'no match'.
A32: 27 | B32: Edit a rule's conditions and re-test. | C32: The new conditions take effect for new leads.
A33: 28 | B33: Create a lead outside business hours (business-hours restriction ON), then wait for hours to resume. | C33: The lead stays 'pending' and is auto-assigned within about 15 minutes of business hours resuming.
A34: E. WEBHOOK & META — EDGE CASES
A35: 29 | B35: Send the SAME signed webhook payload twice. | C35: The second is treated as a duplicate (logged as Duplicate), not a second lead.
A36: 30 | B36: Exceed the per-minute rate limit, then wait a minute and submit again. | C36: Blocked during the burst; accepted again once the minute window resets.
A37: 31 | B37: Rotate/replace a webhook key's secret and submit with the OLD signature. | C37: The old signature is refused after rotation.
A38: 32 | B38: Let a Meta page token expire (or revoke it) and let the sync run. | C38: The app records a clear connection error and does not crash; reconnecting fixes it.
A39: 33 | B39: Map a Meta form field to a CRM field, then pull a lead. | C39: The mapped value lands in the correct CRM field on the promoted lead.

Sheet 8. Money Path (Quote-Pay)
A1: Sl No | B1: Action | C1: Expected Outcome | D1: Result | E1: Remarks
A2: A. QUOTATION TEMPLATES & SETTINGS
A3: 1 | B3: Upload a quotation template (HTML with placeholders) and define its fields. | C3: The template saves and is available when creating a quotation.
A4: 2 | B4: Set the company quotation validity default (7/15/30/60/90 days) and expiry reminder settings. | C4: The settings save.
A5: 3 | B5: Set the quotation number prefix and next number (document numbering). | C5: New quotations use that prefix and sequence.
A6: B. CREATE A QUOTATION
A7: 4 | B7: Create a quotation on a lead, add several line items with quantity and unit price. | C7: Each line total (qty x price) and the grand total are calculated automatically and correctly.
A8: 5 | B8: Check the quotation number. | C8: It uses the company prefix and the next number in sequence.
A9: 6 | B9: Create a quotation WITHOUT setting a validity date. | C9: The validity date is filled automatically from the company default (e.g. today + 30 days).
A10: 7 | B10: Create two quotations at nearly the same time. | C10: They get different sequential numbers; no clash.
A11: 8 | B11: Run Render / Summary / Receipt on the quotation. | C11: The final document is produced from the template with values filled in.
A12: 9 | B12: Enter a negative quantity or a negative unit price on a line item. | C12: Blocked or handled sensibly; totals never go wrong silently.
A13: C. PAYMENT TYPE = LUMPSUM
A14: 10 | B14: Create a lumpsum quotation with a due date and accept it (move to the 'accepted/converted' status). | C14: One payment record is created for the full amount, due on the quotation due date.
A15: 11 | B15: Mark that record Paid. | C15: The payment plan shows fully paid / completed.
A16: D. PAYMENT TYPE = EVEN INSTALLMENTS (rounding matters)
A17: 12 | B17: Create an even-installment quotation for a total that does NOT divide evenly (e.g. 100 over 3) and accept it. | C17: Exactly 3 records are created; they add up to the total, with the LAST record absorbing the rounding (e.g. 33.33, 33.33, 33.34).
A18: 13 | B18: Add up all installment 'expected' amounts. | C18: The sum equals the quotation total exactly, to the last paisa/cent.
A19: 14 | B19: Check the due dates of the installments. | C19: They step forward by the billing period (default 30 days) from today.
A20: E. PAYMENT TYPE = SUBSCRIPTION (rolls forward)
A21: 15 | B21: Create a subscription quotation and accept it. | C21: Two payment records are created first (current period + next period).
A22: 16 | B22: Mark the current period's record Paid. | C22: The next period's record is created automatically — the subscription rolls forward.
A23: 17 | B23: Check that follow-up tasks were created for upcoming periods. | C23: Follow-up tasks (and calendar entries) are created for the upcoming due dates.
A24: F. PAYMENT TYPE = CUSTOM INSTALLMENTS
A25: 18 | B25: Create a custom-installment quotation and accept it. | C25: No installments are pre-created; you add them yourself.
A26: 19 | B26: Add several custom installments with different amounts and due dates. | C26: The quotation/plan total equals the sum of the custom installments.
A27: G. ACCEPTANCE AUTO-CONVERTS THE LEAD (key behaviour)
A28: 20 | B28: On a lead that is NOT yet a customer, accept its quotation. | C28: Accepting the quote automatically converts the lead into a customer AND creates the payment plan.
A29: 21 | B29: Open the new customer after acceptance. | C29: The customer carries the lead's details; the quotation(s) and notes/tasks/attachments moved onto the customer.
A30: 22 | B30: Accept a quotation on a lead whose stage is NOT set to an 'active' quotation status (edge). | C30: Behaviour is consistent with the rule that conversion needs an active quotation; no half-finished state.
A31: H. REVERTING AN ACCEPTED QUOTATION (dangerous edit)
A32: 23 | B32: Take an accepted quotation and change its status BACK to a non-accepted one (e.g. Draft). | C32: The payment plan, its records and the follow-up tasks created for it are removed cleanly.
A33: 24 | B33: Re-accept the same quotation again. | C33: A fresh payment plan is created; there is no leftover duplicate from before.
A34: I. PAYMENT RECORDS — CORNER CASES
A35: 25 | B35: On a plan with several pending records, pay enough to cover the FULL total early. | C35: The plan is marked completed and the remaining pending records (and their tasks) are cancelled automatically.
A36: 26 | B36: Enter a paid amount LARGER than the amount expected on a record. | C36: Handled sensibly (blocked or clearly shows over-payment); the plan maths stays correct.
A37: 27 | B37: Enter a paid amount smaller than expected (part payment). | C37: The remaining amount is tracked correctly; the record/plan reflects the shortfall.
A38: 28 | B38: Attach a receipt file to a payment record. | C38: The file saves against that record.
A39: 29 | B39: Check the plan's 'next due date' after paying one record. | C39: It updates to the earliest still-pending record.
A40: 30 | B40: Delete or cancel a single payment record and watch the plan totals. | C40: The plan recalculates its totals and next due date correctly.
A41: J. VALIDITY, EXPIRY & CURRENCY
A42: 31 | B42: Set a quotation validity date in the PAST. | C42: The quote is treated as expired or clearly warned; not shown as still valid silently.
A43: 32 | B43: Create quotations in two different currencies. | C43: Each quotation keeps its own currency; amounts are not mixed.
A44: 33 | B44: Send a quotation to the customer (e.g. by e-mail) if that option exists. | C44: The send works or a clear status is shown.
A45: K. PRODUCT PRICE CHANGES vs EXISTING QUOTATIONS
A46: 34 | B46: Create a quotation that uses a product at its current price. | C46: The quotation captures that price on its line item.
A47: 35 | B47: Now change the PRODUCT's price in the catalogue, then re-open the EXISTING quotation. | C47: The existing quotation keeps its original price — it does NOT change under the customer's feet.
A48: 36 | B48: Create a NEW quotation for the same product after the price change. | C48: The new quotation prefills/uses the NEW price.
A49: 37 | B49: Check any totals or dashboards that reference the old quotation. | C49: They still reflect the price the quotation was agreed at, not the new catalogue price.
A50: L. THE 'INVOICE' = PAID-PAYMENT LOCK (how billing a quote works)
A51: 38 | B51: Confirm the flow: a quotation is created on a LEAD; accepting it creates the customer AND the payment plan. | C51: There is no separate 'convert to invoice' step — the accepted quotation plus its payment records ARE the billing record. A quote starts on a lead, not directly on a customer.
A52: 39 | B52: On an accepted quotation, mark one payment record as PAID, then try to change the quotation's amounts/line items. | C52: Money edits are BLOCKED once any payment is recorded as paid (a clear 'recorded payment' message).
A53: 40 | B53: On that same quotation with a paid record, try to REVERT its status back to Draft. | C53: Blocked — you cannot revert an accepted quotation to draft once money has been settled (it would destroy paid history).
A54: 41 | B54: On an accepted quotation with NO paid record yet, revert it to Draft. | C54: Allowed — with no settled money, the revert works and its payment plan is cleared.
A55: M. EDIT A QUOTATION BEFORE PAYMENT
A56: 42 | B56: Before any payment is recorded, edit a draft quotation's line items and totals. | C56: The edits save and the totals recompute; the change is recorded in the audit log.

Sheet 9. CRM - Records
A1: Sl No | B1: Action | C1: Expected Outcome | D1: Result | E1: Remarks
A2: A. CUSTOMERS
A3: 1 | B3: Open a customer's 360 detail page. | C3: It shows the customer's products, quotations, payments, projects and support tickets together.
A4: 2 | B4: Set the customer's service level (SLA) as a number and unit (hours/days). | C4: Saved; it is later used for that customer's support ticket deadlines.
A5: 3 | B5: Add products to a customer with quantities. | C5: Products and quantities save on the customer.
A6: 4 | B6: Use Bulk Change Status and Bulk Assign on customers. | C6: Selected customers update correctly.
A7: 5 | B7: Set a customer status and confirm the allowed statuses (Active / Completed / Lost / Upsell In Progress). | C7: The status saves with the right colour/label.
A8: B. CONTACTS
A9: 6 | B9: Create a contact with full details and mark it primary. | C9: Saved with the primary flag.
A10: 7 | B10: Add a second contact for the same company and mark IT primary. | C10: The primary flag behaves sensibly (only the intended one stays primary).
A11: C. PRODUCTS
A12: 8 | B12: Create a product with name, code, price and currency. | C12: Saved.
A13: 9 | B13: Try to create another product with the SAME code. | C13: Blocked; codes are unique.
A14: 10 | B14: Try to create another product with the same NAME in different letter case (e.g. 'Plan A' vs 'plan a'). | C14: Blocked; treated as the same name.
A15: 11 | B15: Enter a price with many decimals and a large value. | C15: Saved and shown correctly, not rounded away or overflowed.
A16: 12 | B16: Bulk Activate / Deactivate / Delete products. | C16: Selected products update correctly.
A17: 13 | B17: Open a product's 'usage' view before deleting. | C17: It shows where the product is used.
A18: 14 | B18: Try to delete a product TYPE that products use. | C18: Blocked; the type is in use.
A19: D. TASKS & FOLLOW-UPS
A20: 15 | B20: Create one task of each type (Task, Call, Meeting, Email, Deadline) with a due date/time. | C20: Each saves with its type and priority.
A21: 16 | B21: Add a reminder (e.g. 1 hour before) with a near due time. | C21: The reminder is saved; the tester can later confirm the reminder notification appears.
A22: 17 | B22: Mark a task complete, then try to reopen it. | C22: Completion works; reopen behaves exactly as the task settings allow.
A23: 18 | B23: Create a follow-up and view Today / Overdue / Upcoming. | C23: It appears in the correct list by date.
A24: 19 | B24: Set a due date/time in the PAST. | C24: Saved and shown overdue, or warned; no silent broken state.
A25: 20 | B25: Turn on 'auto-create a task when a lead is created' and create a lead. | C25: A task is created automatically for the new lead.
A26: 21 | B26: Turn on 'auto-close tasks when a deal is won' and win a deal. | C26: The related open tasks close automatically.
A27: E. NOTES
A28: 22 | B28: Add a note to a lead, give it a type and pin it. | C28: Saved; the pinned note stays on top.
A29: 23 | B29: Attach a file to a note and reopen it. | C29: The attachment saves and can be opened.
A30: F. CALLS & TELEPHONY
A31: 24 | B31: Set up Exotel telephony and an agent number. | C31: Telephony settings save.
A32: 25 | B32: Make a click-to-call from a lead (if a test line exists) and view the call log. | C32: The call is placed and a call log entry is created with direction and duration.
A33: 26 | B33: Add a note or create a task directly from a call log entry. | C33: The note/task is created and linked to the call.
A34: 27 | B34: Turn on call transcription and set scope (All / Admins / Selected users). | C34: The scope saves; transcription only applies to the chosen people.
A35: 28 | B35: After a recorded call, check transcription status and summary. | C35: Status moves Pending -> Processing -> Completed and a transcript/summary appears.
A36: G. MONTHLY GOALS (simple sales target — not the Rewards module)
A37: 29 | B37: Set a monthly goal (target number) for a user for the current month. | C37: Saved for that user and month.
A38: 30 | B38: Try a SECOND goal of the same type for the same user and month. | C38: Blocked; one goal per user/type/month.
A39: 31 | B39: Mark a goal recurring and check next month. | C39: It carries forward to next month when no new goal is set.
A40: 32 | B40: Compare achievement against target on the dashboard. | C40: Achievement is shown against target correctly.
A41: H. SECOND CONTACT FOR A CUSTOMER / LEAD
A42: 33 | B42: Open a customer and add a first contact person; mark them as the primary contact. | C42: The contact is attached to the customer and shown as primary.
A43: 34 | B43: Add a SECOND contact person to the same customer. | C43: Both contacts are attached to the customer.
A44: 35 | B44: Mark the second contact as primary. | C44: Only one contact stays primary — the primary flag moves to the second, and the first is no longer primary.
A45: 36 | B45: Remove one contact from the customer. | C45: Only that contact is removed; the other stays attached.
A46: 37 | B46: For a LEAD, check how contact details are held. | C46: A lead carries its own single set of contact details (name, e-mail, phone). Note that multiple separate contact people are a Customer concept, not a Lead one.

Sheet 10. Project
A1: Sl No | B1: Action | C1: Expected Outcome | D1: Result | E1: Remarks
A2: A. PROJECT SETUP
A3: 1 | B3: Create project statuses and task statuses, each with a colour and order; mark flags 'closed' and 'cancelled'. | C3: They save; a 'cancelled' status must also be 'closed' (the app enforces this). | D3: Blocked | E3: statuses are seeded by default when an org is registered
A4: 2 | B4: Open project settings and set defaults (view, priority, visibility) and rules (templates, comments, dependencies, auto-close, auto-archive). | C4: All settings save. | D4: Blocked | E4: there is no project settings
A5: B. PROJECTS
A6: 3 | B6: Create a project with name, status, priority, dates, manager, members and a linked customer. | C6: Saved with all details. | D6: Pass
A7: 4 | B7: Try another active project with the SAME name. | C7: Blocked; active project name must be unique. | D7: Pass | E7: blocked during creation with error being dispalyed in the name field
A8: 5 | B8: Set a project's visibility to Private, then log in as a non-member. | C8: The non-member cannot see the private project. | D8: Fail | E8: users of the org can view the project
A9: 6 | B9: Set an expected end date in the past and leave the project open. | C9: It shows as Overdue. | D9: Pass
A10: 7 | B10: Archive a project, then create a NEW project reusing its name. | C10: The name can be reused once the old one is archived. | D10: Blocked | E10: no archive option
A11: C. PROGRESS CALCULATION
A12: 8 | B12: Set progress method to 'Task Completion' and mark some tasks complete. | C12: The percentage reflects the share of completed lowest-level tasks. | D12: Fail
A13: 9 | B13: Add sub-tasks under a parent and complete some. | C13: Only the lowest-level tasks count; the parent does not double-count. | D13: Fail | E13: Task progress is marked as 100 but project progress is not being updated
A14: 10 | B14: Cancel a task and re-check the percentage. | C14: Cancelled tasks are left out of the percentage entirely. | D14: Fail
A15: 11 | B15: Switch progress method to 'Manual' and set a number. | C15: The manual percentage stays as entered and is not auto-changed. | D15: Blocked | E15: no progress edit option
A16: D. TASKS, SUB-TASKS & MULTIPLE ASSIGNEES
A17: 12 | B17: Create a task with subject, status, priority (Low/Medium/High/Urgent) and due date. | C17: Saved. | D17: Pass
A18: 13 | B18: Add several assignees to one task and set one as the main owner. | C18: All assignees save; the main owner stays in the set. | D18: Fail | E18: doesnt support multiple assignees in the ui
A19: 14 | B19: Build a task tree: task -> sub-task -> sub-sub-task. | C19: The tree is built with correct parent/child links. | D19: Pass
A20: 15 | B20: Look at a parent task's rolled-up progress bar. | C20: It shows progress from its sub-tasks and matches the project bar's logic. | D20: Pass
A21: E. DEPENDENCIES — ERROR CHECKS
A22: 16 | B22: Make Task A depend on Task B. | C22: Saved (A is blocked by B). | D22: Pass
A23: 17 | B23: Try to make a task depend on ITSELF. | C23: Blocked with a clear message. | D23: Pass | E23: the task cannot be blocked on itself as the task in not displayed in the dorpdown
A24: 18 | B24: Try to add the SAME dependency twice. | C24: Blocked. | D24: Pass | E24: the same task is not displayed
A25: 19 | B25: Create a loop: A depends on B, B depends on A. | C25: Blocked; the loop is refused. | D25: Pass | E25: the task is not displayed
A26: 20 | B26: Try to depend on a task in another project (with cross-project OFF). | C26: Blocked; cross-project dependencies are not allowed unless enabled. | D26: Pass | E26: the cross proejct task is not being displayed
A27: 21 | B27: Turn cross-project dependencies ON in settings and retry. | C27: Now allowed within the same company. | D27: Blocked | E27: no option for that
A28: 22 | B28: Try to delete a task that another task depends on. | C28: Blocked until the dependency is removed. | D28: Pass | E28: failed with a clear error message
A29: F. COMPLETION RULES
A30: 23 | B30: Try to complete a parent task while its sub-tasks are open. | C30: Blocked; the app names the sub-tasks that are not done. | D30: Pass | E30: failed with a clear error message
A31: 24 | B31: Try to complete a task while a task it depends on is still open. | C31: Blocked; the app names the blocking task. | D31: Pass | E31: failed with a clear error message
A32: 25 | B32: Cancel a task even though its sub-tasks are open. | C32: Cancelling is allowed — not blocked by open sub-tasks. | D32: Pass
A33: G. COLLABORATION & UPDATES
A34: 26 | B34: Add a comment to a task, attach a file, and paste an image into the comment box. | C34: Comment, file and pasted image all save and show. | D34: Pass
A35: 27 | B35: Check the comment-count badge on a task in the list. | C35: The badge shows the correct comment count without opening the task. | D35: N/A | E35: there is no commnt count badge in list view but there is one in detail apge and it works
A36: 28 | B36: File a project status update as the manager. | C36: Saved; the manager/members are notified. | D36: Pass
A37: 29 | B37: Turn on 'collect progress' with a schedule and holiday dates. | C37: The reminder schedule saves; the tester can later confirm reminders arrive and skip holidays.
A38: H. BULK ACTIONS
A39: 30 | B39: Select several tasks and Bulk Assign / Change Status / Delete. | C39: Selected tasks update correctly. | D39: Blocked | E39: not implemeted
A40: 31 | B40: Bulk import projects from a file (valid + a few bad rows). | C40: Valid rows import; bad rows are reported; nothing is silently corrupted. | D40: Blocked | E40: not implemeted

Sheet 11. Helpdesk
A1: Sl No | B1: Action | C1: Expected Outcome | D1: Result | E1: Remarks
A2: A. TICKET SETUP
A3: 1 | B3: Create ticket types (each with a default priority) and statuses (mark one default, one resolved, one on-hold). | C3: They save; only one default status is allowed. | D3: Pass
A4: B. RAISE & WORK A TICKET
A5: 2 | B5: Raise a ticket for a customer (reported-for = Client) with subject, channel (Email/WhatsApp/Phone) and priority. | C5: Created with all details. | D5: Pass
A6: 3 | B6: Create a ticket of a type that has a default priority. | C6: It automatically gets that type's default priority. | D6: N/A | E6: no priority for type
A7: 4 | B7: Assign the ticket to an agent, then re-assign to a team. | C7: Assignment and re-assignment save. | D7: Fail | E7: assignment to an agent is working but no team assignment option
A8: 5 | B8: Link the ticket to a lead / customer / project. | C8: The linked record shows on the ticket. | D8: Pass
A9: 6 | B9: Add comments and attachments. | C9: They save and show in order. | D9: Pass
A10: 7 | B10: Create a parent ticket and a child ticket under it. | C10: The parent/child link is shown. | D10: Blocked | E10: only linked tasks can be created no parent/child ticekts
A11: C. SERVICE LEVEL (SLA) — THE KEY BEHAVIOUR
A12: 8 | B12: Set a customer's SLA (e.g. 4 hours), then raise a ticket for that customer. | C12: The ticket deadline is based on that customer's own SLA. | D12: Pass
A13: 9 | B13: Change the SAME customer's SLA afterwards and open the earlier ticket. | C13: The earlier ticket keeps its original deadline (the SLA was snapshotted when it was raised). | D13: Fail | E13: no edit/add option for sla
A14: 10 | B14: Move a ticket into an 'on-hold' status, wait, then move it back. | C14: The time spent on hold is added back to the deadline (the clock pauses while on hold). | D14: Pass
A15: 11 | B15: Put a ticket on hold and off hold twice. | C15: All the paused time adds up correctly across multiple holds. | D15: Pass
A16: 12 | B16: Let a ticket pass its deadline without resolving (and not on hold). | C16: It is flagged as breached and its priority is raised to High automatically.
A17: 13 | B17: Move a ticket into a 'resolved' status. | C17: The resolution date and time are set automatically. | D17: Pass | E17: recorded and resolved tickets cannot be edited
A18: 14 | B18: Re-open a resolved ticket. | C18: The re-open count goes up by one. | D18: Blocked | E18: recorded and resolved tickets cannot be edited
A19: D. BULK, LIST & DASHBOARD
A20: 15 | B20: Filter tickets by status, priority and assignee; search by subject. | C20: The list updates correctly. | D20: Pass
A21: 16 | B21: Bulk Assign / Change Status / Change Priority / Delete tickets. | C21: Selected tickets update correctly. | D21: Partial | E21: no bulk status change, piroity and deletion
A22: 17 | B22: Open the Helpdesk dashboard / boards. | C22: Shows counts by status, breached tickets and tickets needing attention. | D22: Pass
A23: E. PARENT & CHILD TICKETS
A24: 18 | B24: Create a parent ticket, then create two child tickets under it. | C24: The children show their parent; the parent lists its children. | D24: Blocked | E24: only linked tasks can be created no parent/child ticekts
A25: 19 | B25: Change a child ticket's status. | C25: The child updates; the parent reflects the change per the app's rule (e.g. a roll-up or activity note). | D25: Blocked | E25: only linked tasks can be created no parent/child ticekts
A26: 20 | B26: Try to make a ticket its own parent, or create a parent-child loop. | C26: Blocked; a ticket cannot be its own parent and loops are refused. | D26: Blocked | E26: only linked tasks can be created no parent/child ticekts
A27: 21 | B27: Resolve all child tickets, then look at the parent. | C27: The parent's state behaves consistently with its children being done (confirm the intended behaviour). | D27: Blocked | E27: only linked tasks can be created no parent/child ticekts
A28: 22 | B28: Delete a parent ticket that has children. | C28: The app handles it clearly (blocks, or detaches/rehomes the children) rather than leaving orphans or crashing. | D28: Blocked | E28: only linked tasks can be created no parent/child ticekts

Sheet 12. LMS (Training)
A1: Sl No | B1: Action | C1: Expected Outcome | D1: Result | E1: Remarks
A2: A. BUILD A COURSE (admin)
A3: 1 | B3: Create a course with title, description, thumbnail; add modules; add a video and a PDF to a module. | C3: All save in order.
A4: 2 | B4: Upload a very large video. | C4: Upload works (or shows clear progress/limit); the video plays after processing.
A5: 3 | B5: Try to save a course with no title. | C5: Blocked; title required.
A6: 4 | B6: Mark the course Sequential, Mandatory and set a deadline. | C6: The settings save.
A7: 5 | B7: Publish the course, then set it back to Draft. | C7: Publish/draft changes correctly; only published courses are visible to learners.
A8: B. ASSIGN & ENROL
A9: 6 | B9: Assign the course to specific users, then to a whole role, then to everyone (universal). | C9: Each method enrols the right learners.
A10: 7 | B10: Set a per-learner deadline different from the course deadline. | C10: The learner's own deadline overrides the course deadline.
A11: C. LEARNER EXPERIENCE
A12: 8 | B12: Log in as a learner, open My Trainings and start a video. | C12: The video plays.
A13: 9 | B13: Watch part of a video, leave, and return later. | C13: Playback resumes where you stopped.
A14: 10 | B14: Finish all videos in a course. | C14: The course shows Completed (100%).
A15: 11 | B15: Let a course deadline pass without finishing. | C15: The course shows Overdue for that learner.
A16: 12 | B16: For a Sequential course, try to jump ahead before finishing earlier videos. | C16: Blocked; you must go in order.
A17: D. MANDATORY COURSE (access block)
A18: 13 | B18: Assign a Mandatory course to a test user and log in as them. | C18: The mandatory course is clearly flagged; confirm whether access to the rest of the app is blocked as intended.
A19: E. QUIZZES
A20: 14 | B20: Add a quiz with single-choice, multiple-choice and true/false questions; set a pass mark and max attempts. | C20: The quiz saves with all question types.
A21: 15 | B21: As a learner, pass the quiz. | C21: Score is calculated and shown; a passing score is marked passed.
A22: 16 | B22: Fail and retake up to the attempt limit, then try once more. | C22: Retakes work up to the limit; the extra attempt is blocked.
A23: 17 | B23: Start a timed quiz and let the time run out. | C23: The quiz ends when time is up and is scored on what was answered.
A24: F. REMINDERS & ADMIN VIEW
A25: 18 | B25: As admin, 'nudge' a learner. | C25: The learner gets a nudge notification.
A26: 19 | B26: Open the training dashboard and learners list. | C26: Completion and progress across learners are shown correctly.
A27: 20 | B27: Log in as a normal staff user and try to open the training admin screens (course builder, learners). | C27: The admin-only training screens are hidden or blocked for staff users.
A28: G. QUIZ / QUESTIONNAIRE — CONFIRM IT IS AVAILABLE FIRST
A29: 21 | B29: From a published course, look for the Quiz/Questionnaire section as a learner and as an admin. | C29: Confirm the quiz feature is actually reachable in THIS build. (If quizzes are modelled but not yet exposed in the app, mark FAIL/N-A and note it — then skip the quiz rows in section E.)
A30: 22 | B30: As an admin, add a quiz to a course with a mix of single-choice, multiple-choice and true/false questions and set points per question. | C30: The quiz saves with all question types and per-question points.
A31: 23 | B31: Set a pass mark, a max number of attempts, and a time limit. | C31: All three save.
A32: 24 | B32: As a learner, submit a quiz with the correct answers. | C32: The score is calculated from the per-question points and marked passed if it meets the pass mark.
A33: 25 | B33: Submit a multiple-choice question with only SOME of the correct options. | C33: It is scored per the app's rule for partial answers (confirm the intended behaviour).
A34: 26 | B34: Use up all attempts, then try again; also let the timer expire mid-attempt. | C34: Extra attempts beyond the limit are blocked; an expired timer auto-submits and scores what was answered.

Sheet 13. Automations
A1: Sl No | B1: Action | C1: Expected Outcome | D1: Result | E1: Remarks
A2: A. CONFIRM THIS BUILD INCLUDES AUTOMATIONS
A3: 1 | B3: Open the Automations section from the menu and confirm the rule list loads. | C3: The rule list opens and loads. (If this build does not include the module yet, it will error or be missing — mark FAIL, note the build, and mark the rest Blocked.) | D3: Pass
A4: 2 | B4: Open the 'new rule' builder. | C4: The builder opens with Trigger, Condition and Action sections. | D4: Pass
A5: B. TRIGGER — EVENTS & SCHEDULES
A6: 3 | B6: Create a rule with an EVENT trigger on Lead for 'create'. Set it Active. Create a matching lead. | C6: The rule runs and its action is applied to the new lead. | D6: Pass
A7: 4 | B7: Change the trigger to fire on 'update' and watch a SPECIFIC field (e.g. status). Edit a lead's status. | C7: The rule fires. Now edit a DIFFERENT field on another lead — the rule does NOT fire (it only fires when the watched field changes). | D7: Pass
A8: 5 | B8: Create a SCHEDULE trigger and pick a frequency (hourly / daily / weekly / monthly). | C8: The scheduled rule saves and shows a next-run time. | D8: Pass
A9: 6 | B9: Try each trigger model offered (e.g. Lead, Customer, Task, Quotation). | C9: Each allowed model can be chosen as the trigger. | D9: Pass
A10: C. CONDITIONS
A11: 7 | B11: Add a condition on a normal field (e.g. Lead source is one value). | C11: The condition saves; the live preview shows how many records match now. | D11: Pass
A12: 8 | B12: Combine two conditions with AND, then switch the group to OR. | C12: AND needs all, OR needs any; the preview count changes to match. | D12: Pass
A13: 9 | B13: Use an operator that takes a LIST of values (e.g. 'is one of') and pick several. | C13: Multiple values are accepted. | D13: Pass
A14: 10 | B14: Use a date-based condition (e.g. created in the last N days). | C14: The date condition works in the preview. | D14: Pass
A15: 11 | B15: Use a CUSTOM field as a condition. | C15: The custom field is offered and can be used in a condition. | D15: Fail | E15: custom field isbeing passed as uuid in the payload { "code": 400, "message": "Validation Error", "errors": { "condition": [ "Unknown field 'cf:b282386a-96f4-44a5-b49c-5df4912c56f9' for model 'lead'." ] } }
A16: 12 | B16: Leave the condition empty (match all) and check the preview. | C16: An empty condition matches every record of that model; the preview shows the full count. | D16: Pass
A17: D. ACTIONS (only two kinds — no delete)
A18: 13 | B18: Add an 'update fields' action that sets a value on the triggering record, and save. | C18: The action saves; the rule becomes valid and saveable. | D18: Pass
A19: 14 | B19: Add a 'create row' action that creates a related record, and save. | C19: The create action saves.
A20: 15 | B20: Look for any action that DELETES records. | C20: There is NO delete action — automations can only create or update, never delete. Confirm delete is not offered. | D20: Pass
A21: 16 | B21: Save a rule that has a trigger but NO valid action. | C21: The app warns the rule is not complete/saveable until an action is added. | D21: Pass
A22: 17 | B22: Add an 'update fields' action with an EMPTY set of fields. | C22: Blocked; an update action needs at least one field to set. | D22: Pass | E22: the ui doesnt allow that
A23: E. RUN, PRIORITY & TIMING
A24: 18 | B24: Set a rule to Paused or Draft and trigger its event. | C24: The rule does NOT run — only Active rules run. | D24: Pass
A25: 19 | B25: After triggering an event rule, watch how quickly the action is applied. | C25: The action applies a short moment AFTER the change is saved (rules run in the background), not necessarily instantly. Confirm it does apply. | D25: Pass | E25: after 30secs
A26: 20 | B26: Create two ACTIVE rules that both set the SAME field on the same record, with different priorities. | C26: The higher-priority rule (lower number) wins the field; both runs are logged.
A27: 21 | B27: Try to give two rules the SAME priority number. | C27: Blocked; each rule must have a unique priority in the company. | D27: Pass
A28: 22 | B28: Try to create two rules with the same NAME. | C28: Blocked; rule names are unique in the company. | D28: Pass | E28: no error handeling in the forntend
A29: F. EXECUTION LOG & EXACTLY-ONCE
A30: 23 | B30: Open the execution logs after some runs. | C30: Each run is listed as Applied / Skipped (no match) / Failed, with how many records were affected and what changed. | D30: Pass
A31: 24 | B31: Trigger the exact same event twice for the same record (e.g. a duplicate save). | C31: The rule applies only once for that event — it is not double-applied. | D31: Pass
A32: 25 | B32: Open a run's details. | C32: It shows the before/after of each changed field for the affected records. | D32: Pass
A33: G. SAFETY — FAILURES, CIRCUIT-BREAKER, BIG RUNS
A34: 26 | B34: Make a rule fail on purpose (e.g. an action that cannot complete) FIVE times in a row. | C34: After 5 failures in a row the rule auto-pauses itself (a safety circuit-breaker), instead of failing forever. | D34: Pass | E34: not displaying why it failed
A35: 27 | B35: Fix the rule and let it succeed once. | C35: The failure count resets to zero; the rule can run normally again.
A36: 28 | B36: Have TWO active rules where one fails and one succeeds on the same event. | C36: The failing rule's error does not stop the other rule — a bad rule never blocks the rest.
A37: 29 | B37: Create a SCHEDULE rule whose condition matches a very large number of records. | C37: It processes a capped batch per run (a safety limit, around 5000 rows) rather than trying everything at once; note if more remain.
A38: H. EDIT, VERSIONS & VALIDITY
A39: 30 | B39: Edit an active rule's conditions and save. | C39: The edit saves; a new version is recorded; older execution logs still show which version ran. | D39: Fail | E39: no version indication
A40: 31 | B40: Create a rule that uses a custom field, then DELETE that custom field. | C40: The rule is marked invalid with a warning (it points to a removed field); it stops acting rather than misbehaving silently. | D40: Blocked | E40: test 11
A41: 32 | B41: Delete a rule. | C41: The rule is removed from the list. | D41: Blocked | E41: no option
A42: 33 | B42: Filter the rules list by status (Active/Paused/Draft) and by model; search by name. | C42: The list and the status-tab counts update correctly. | D42: Pass
A43: I. MORE CORNER CASES
A44: 34 | B44: Rename a custom field that an active rule uses (instead of deleting it). | C44: The rule keeps working if the field still exists under the hood, or is flagged if the reference breaks — it does not silently act on the wrong field. | D44: Blocked | E44: test 11
A45: 35 | B45: Create a 'create row' action that makes a related record (e.g. a task when a lead is created) and trigger it. | C45: The related record is created with the values you set. | D45: Pass
A46: 36 | B46: Confirm a scheduled rule actually fires on its stated frequency (hourly/daily/weekly/monthly). | C46: The rule runs at about the right time and the next-run time advances.
A47: 37 | B47: If a global 'pause all automations' switch exists, turn it on and trigger events. | C47: No rules run while globally paused; turning it off resumes them. | D47: N/A | E47: no option
A48: 38 | B48: Bump a rule's priority number up and down and confirm conflict-winner changes. | C48: The lower-numbered rule always wins when two rules set the same field.

Sheet 14. Goals & Rewards
A1: Sl No | B1: Action | C1: Expected Outcome | D1: Result | E1: Remarks
A2: A. CONFIRM THIS BUILD INCLUDES GOALS & REWARDS
A3: 1 | B3: Open Goals & Rewards > My Progress and confirm it loads. | C3: The screen opens and shows progress. (If this build does not include the module yet, it will error or be missing — mark FAIL, note the build, and mark the rest Blocked.) | D3: Pass
A4: 2 | B4: Open My Team and Approvals (visible only to managers / approvers). | C4: Each opens for the right people; a person with no team does not see My Team; a non-approver does not see Approvals. | D4: Pass
A5: B. CREATE A MILESTONE (admin/exec only)
A6: 3 | B6: Create a one-shot milestone with a measure, a target and a reward description; save as Draft, then Activate. | C6: It saves as Draft and can be activated. | D6: Pass
A7: 4 | B7: Try each measure: Won Deal Value, Deals Won Count, Conversions Count, Cash Collected. | C7: Each measure can be chosen; money measures show currency, count measures show a number. | D7: Pass
A8: 5 | B8: Create a repeatable milestone and pick a period (weekly / monthly / bimonthly / quarterly / half-yearly / yearly / custom). | C8: The repeatable milestone saves with its period. | D8: Pass
A9: 6 | B9: Create one repeatable WITH expiry and one WITHOUT expiry; let a period roll over. | C9: 'With expiry' resets progress to zero each new period; 'without expiry' keeps one running lifetime total. Confirm both behave that way.
A10: 7 | B10: Add a condition to a milestone (e.g. only deals from a chosen source). | C10: Only matching events count. Confirm the builder does NOT offer owner/assignee fields or 'relative time' functions for milestone conditions. | D10: Pass
A11: 8 | B11: Try to create two milestones with the same NAME. | C11: Blocked; milestone names are unique in the company. | D11: Pass
A12: C. WHO GETS THE CREDIT — FROZEN OWNER (key behaviour)
A13: 9 | B13: With Anna owning a lead, win a qualifying deal on it. Then change the lead's OWNER to Bob. Check whose milestone the win counted toward. | C13: The credit stays with ANNA — the owner at the moment the deal was won. Re-assigning the lead afterwards does NOT move the credit to Bob.
A14: 10 | B14: Win a qualifying deal on a lead that has NO owner. | C14: The event is recorded but credited to no one (it does not wrongly credit whoever touched it).
A15: 11 | B15: Count the same business event twice (e.g. a duplicate save of the won deal). | C15: It counts only ONCE toward the milestone — no double counting.
A16: D. PROGRESS & TIMING (updates on a schedule, not instantly)
A17: 12 | B17: As a participant, win a qualifying deal and watch My Progress. | C17: The progress value climbs toward the target. It may take a short while to update because progress refreshes on a schedule (every few hours), not instantly.
A18: 13 | B18: Change the milestone's refresh cadence (3 / 6 / 12 / 24 hours) for a NEW milestone. | C18: New milestones use the chosen cadence.
A19: 14 | B19: Reach the target of a milestone. | C19: Progress shows 100% and the reward becomes Achieved.
A20: E. PARTICIPANTS & ENROLMENT
A21: 15 | B21: Assign a milestone to a TEAM. | C21: Every member of the team becomes an individual participant. | D21: Blocked | E21: no team selection
A22: 16 | B22: Add a participant, then do qualifying work that happened BEFORE they were enrolled. | C22: Only work from AFTER they were enrolled counts toward their progress.
A23: F. REWARD STATES & APPROVAL FLOW
A24: 17 | B24: For a milestone WITHOUT approval required, reach the target. | C24: The reward goes straight to Approved automatically (no manual approval needed).
A25: 18 | B25: For a milestone WITH approval required, reach the target. | C25: The reward waits at Achieved until an approver approves it.
A26: 19 | B26: Approve an achieved reward, then fulfil it. | C26: The reward moves Achieved -> Approved -> Fulfilled.
A27: 20 | B27: Reject an achieved reward. | C27: The reward becomes Void.
A28: 21 | B28: After a reward is Void, let the same person reach the same target again. | C28: A fresh reward can be granted for that period (the voided one freed the slot).
A29: 22 | B29: Try to approve a reward that is NOT in the Achieved state (e.g. already Approved). | C29: Blocked; only an Achieved reward can be approved or rejected.
A30: G. GRANDFATHER — EARNED REWARDS DON'T CHANGE
A31: 23 | B31: Reach a target so a reward is Achieved, then REVERSE/cancel the qualifying deal (e.g. un-win or refund). | C31: The reward STAYS earned — once achieved it is not taken back by a later reversal (progress may drop, but the reward is not revoked).
A32: 24 | B32: Reach a target, then EDIT the milestone's reward text or target. | C32: The already-earned reward keeps its ORIGINAL reward and target; the edit only affects future achievements.
A33: H. LEVELS / TRACKS (test hard)
A34: 25 | B34: Create a level track and add milestones as Level 1, Level 2, Level 3. | C34: They save in order with their level numbers.
A35: 26 | B35: As a participant, look at Level 2 before completing Level 1. | C35: Level 2 is locked until Level 1 is completed — you climb the ladder in order.
A36: 27 | B36: Set the org Unlock Gate to 'Achievement', complete Level 1's target, then check Level 2. | C36: With gate = Achievement, simply REACHING Level 1's target unlocks Level 2.
A37: 28 | B37: Set the org Unlock Gate to 'Approval'. Reach a level's target but do NOT get the reward approved yet. | C37: With gate = Approval, the next level stays locked until the reward is APPROVED, not just achieved. (Changing the gate applies immediately.)
A38: 29 | B38: Create a standalone milestone that is NOT in any track. | C38: It is never level-locked and works on its own.
A39: I. ENGINE SETTINGS — LIVE vs FIXED-AT-CREATION
A40: 30 | B40: Change the Approver Mode (Reporting manager / Executive leadership / Either). | C40: The change applies immediately to all campaigns (it is a live setting).
A41: 31 | B41: Change the Unlock Gate. | C41: The change applies immediately at the next unlock check (live).
A42: 32 | B42: Change the default refresh cadence or the default 'approval required' AFTER milestones exist. | C42: Existing milestones keep the value they were created with (not retroactive); only new milestones use the new default.
A43: J. APPROVER AUTHORITY (who may approve)
A44: 33 | B44: Set Approver Mode = 'Reporting manager'. As a subordinate's MANAGER, approve their reward. | C44: The manager (anywhere up the chain) can approve.
A45: 34 | B45: As the SAME person who earned the reward, try to approve your own. | C45: Blocked; you are not above yourself in the chain.
A46: 35 | B46: As a PEER (not a manager, not admin/exec), try to approve someone's reward. | C46: Blocked under 'Reporting manager' and 'Executive leadership' modes.
A47: 36 | B47: Set Approver Mode = 'Executive leadership'. As an ordinary manager (not exec/admin), try to approve. | C47: Blocked; only Executive Leadership or a System Admin may approve in this mode.
A48: 37 | B48: A participant who has NO manager reaches a target needing approval. Check who can clear it. | C48: It escalates to a System Admin / Executive Leadership; it does not get stuck with no possible approver.
A49: K. LIFECYCLE
A50: 38 | B50: Archive an active milestone. | C50: It stops all future progress but keeps its history; it cannot be hard-deleted.
A51: 39 | B51: Open a past (closed) period of a repeatable milestone. | C51: The closed period is kept with its final value, target and reward outcome.
A52: 40 | B52: Create a milestone with a broken/invalid condition. | C52: A warning is shown but the screen does not crash (it fails safely).
A53: L. MORE CORNER CASES
A54: 41 | B54: Assign a milestone to a team of several people, then open participants. | C54: One participant row is created per team member.
A55: 42 | B55: Set Approver Mode = 'Either', then approve a reward as a manager, and separately as an Exec/Admin. | C55: Both a manager and an Exec/Admin can approve in 'Either' mode.
A56: 43 | B56: Reverse a deal that had pushed a participant PAST target (reward already Achieved). | C56: The progress value may drop, but the already-Achieved reward is NOT revoked (achievement latches).
A57: 44 | B57: On a level track, complete Level 1 for a user, then view their level cache/position. | C57: Their unlocked level advances to Level 2; the position matches what they have actually completed.
A58: 45 | B58: Two people on the same milestone: one reaches target, the other does not. | C58: Only the achiever gets a reward grant; the other stays in progress.

Sheet 15. Billing
A1: Sl No | B1: Action | C1: Expected Outcome | D1: Result | E1: Remarks
A2: A. PLANS & WHAT THEY UNLOCK
A3: 1 | B3: Open Billing and view the plans with monthly and yearly prices. | C3: Plans and prices are shown clearly. | D3: Pass
A4: 2 | B4: View the current subscription and included features. | C4: The current plan, status and included features are shown. | D4: Pass | E4: Features are not displayed
A5: 3 | B5: On a plan WITHOUT WhatsApp (or Projects / Quotations / LMS), try to use that feature. | C5: Blocked with a clear message and an upgrade prompt — not a broken page. | D5: Pass
A6: 4 | B6: Upgrade to a plan that includes the feature, then use it. | C6: The feature becomes available after upgrade. | D6: Pass
A7: 5 | B7: On a plan with a user limit, try to add one more user than allowed. | C7: Blocked or clearly warned that the seat limit is reached. | D7: Pass
A8: B. TRIAL & MANDATE
A9: 6 | B9: Start a free trial for a new company. | C9: The trial starts and its end date is shown. | D9: Pass
A10: 7 | B10: Check whether the trial needs a payment mandate before it activates. | C10: If required, the app asks for a mandate and does not fully activate until it is verified. | D10: Pass
A11: 8 | B11: Let a trial reach its end date. | C11: The trial ends and the company moves to the correct next state (grace or suspended).
A12: C. PAYMENT MANDATE (RAZORPAY)
A13: 9 | B13: Start setting up a mandate (UPI / Card / e-Mandate). | C13: The payment page opens; a small authorisation charge (about 1 rupee) is taken. | D13: Pass
A14: 10 | B14: Complete the mandate and return. | C14: The mandate shows active/verified and the subscription updates. | D14: Pass
A15: 11 | B15: Cancel the mandate. | C15: The mandate is cancelled and the app reflects it. | D15: Fail | E15: mandate cancellation option is not available
A16: D. SEATS, INVOICES & LAPSE
A17: 12 | B17: Add a user on a paid plan. | C17: The seat count reflects the new user for the next cycle. | D17: Pass
A18: 13 | B18: Remove a user mid-cycle. | C18: The change is recorded; confirm the rule (no mid-cycle credit for removals) matches expectations. | D18: Pass
A19: 14 | B19: Open invoices and download an invoice PDF. | C19: The invoice opens with correct totals (subtotal + tax - discount = total). | D19: Fail | E19: the paid amount doesnt calculate the tax but the invoice do
A20: 15 | B20: View payment history. | C20: Past payments are listed with amount, method and status. | D20: Pass | E20: method is not displayed/stored
A21: 16 | B21: Move a company to Suspended / Cancelled / Past-due (with admin help). | C21: Paid features stop working, but the company's data is NOT deleted. | D21: Fail | E21: error in backend - rls
A22: 17 | B22: Bring the subscription back to Active. | C22: Paid features work again and the data is intact. | D22: Blocked | E22: issue 16 must be fixed

Sheet 16. Communications
A1: Sl No | B1: Action | C1: Expected Outcome | D1: Result | E1: Remarks
A2: A. EMAIL
A3: 1 | B3: Connect a Gmail mailbox (sign in with Google) in email settings. | C3: The mailbox connects and shows active. | D3: Pass
A4: 2 | B4: Look at the provider choices (Gmail / Outlook / Custom). | C4: Only options that actually work should be selectable; a non-working option should not be offered, or should say 'coming soon'. | D4: Pass
A5: 3 | B5: Open the inbox after connecting. | C5: Messages load into the inbox. | D5: Pass
A6: 4 | B6: Open a message and its thread; download an attachment. | C6: Message, thread and attachment open correctly. | D6: Blocked | E6: messages are being sent but the mails are not visible in clozr
A7: 5 | B7: Reply to a message and send a new e-mail from inside the app. | C7: The reply and new e-mail are sent. | D7: N/A | E7: incominng mails are not poosible
A8: 6 | B8: As a normal user (not admin), check which mailboxes you can see. | C8: You see your own mailbox plus the company default mailbox — not every other person's mailbox. | D8: Pass
A9: 7 | B9: Disconnect the mailbox. | C9: The mailbox is removed and its inbox no longer loads. | D9: Blocked | E9: no disconnect option in mail
A10: B. WHATSAPP
A11: 8 | B11: Set up the WhatsApp business account. | C11: The account connects. | D11: Blocked
A12: 9 | B12: Open the WhatsApp conversations inbox. | C12: Conversations load with unread counts. | D12: Pass
A13: 10 | B13: Open a conversation; assign to an agent, unassign, then star it. | C13: Assign, unassign and star all work. | D13: Blocked
A14: 11 | B14: Send a text, a template, an image and a document. | C14: Each message type sends and appears in the conversation. | D14: Blocked
A15: 12 | B15: Try to send a plain text message outside an active conversation window. | C15: The app requires a template message as WhatsApp rules demand, or explains why. | D15: Blocked
A16: 13 | B16: Sync WhatsApp templates from the provider. | C16: The templates list updates. | D16: Blocked
A17: 14 | B17: On a plan WITHOUT WhatsApp, open the WhatsApp inbox. | C17: Blocked with an upgrade message. | D17: Blocked
A18: C. TELEPHONY (covered in CRM - Records too)
A19: 15 | B19: Confirm click-to-call, call logs and recording appear where a call is made from a lead or customer. | C19: Calls are logged against the right record.
A20: D. EMAIL — DEEPER
A21: 16 | B21: Search the inbox, mark a message read/unread, and star/flag a message. | C21: Search, read state and star all work and persist.
A22: 17 | B22: Forward a message and reply-all on a thread. | C22: Forward and reply-all send correctly and stay on the right thread.
A23: 18 | B23: Open a message with a large attachment and download it. | C23: The attachment downloads; very large attachments are handled without breaking the page.
A24: 19 | B24: As an admin, connect a SECOND company mailbox; as a normal user, check which mailboxes are visible. | C24: Admins see all company mailboxes; a normal user sees only their own plus the company default.
A25: 20 | B25: Send an e-mail to an address that will bounce / with the mailbox disconnected. | C25: A clear failure/status is shown; the app does not silently swallow the error.
A26: E. WHATSAPP — DEEPER
A27: 21 | B27: Try to send a free-text message to a contact whose last message was more than 24 hours ago. | C27: The app requires an approved TEMPLATE message (WhatsApp's 24-hour window rule), or clearly explains why. | D27: Pass
A28: 22 | B28: Send a template message and watch its delivery/read status. | C28: The status updates (sent/delivered/read) as the message progresses. | D28: Pass
A29: 23 | B29: Receive an inbound WhatsApp with an image/document and open it. | C29: The media loads through the app safely. | D29: Pass
A30: 24 | B30: Use a canned response, assign the conversation to an agent, star it, and mark it read. | C30: Canned response, assignment, star and read state all work; the unread badge updates. | D30: Blocked
A31: 25 | B31: Try to WhatsApp a lead marked 'unsubscribed'. | C31: The send is blocked with an 'unsubscribed' message (confirmed rule). | D31: Blocked
A32: F. TELEPHONY (EXOTEL) — DEEPER
A33: 26 | B33: Make a call from a lead, then check the call log, recording and any transcription/summary. | C33: The call is logged against the lead with duration; recording/transcription appear per the settings. | D33: Pass
A34: 27 | B34: Add a note or task straight from the call log entry. | C34: The note/task is created and linked to the call. | D34: Fail

Sheet 17. Reports
A1: Sl No | B1: Action | C1: Expected Outcome | D1: Result | E1: Remarks
A2: A. DASHBOARDS
A3: 1 | B3: Open the main Dashboard after login. | C3: It loads with cards, numbers and charts — not blank or broken. | D3: Pass
A4: 2 | B4: Change the date range / filters on a dashboard. | C4: Numbers and charts update for the chosen range. | D4: Pass
A5: 3 | B5: Change a record (e.g. mark a lead won) and refresh the dashboard right away. | C5: The number may take a few seconds to update (figures refresh on a short delay), then corrects itself. | D5: Pass
A6: 4 | B6: Open the sales, delivery (PMO) and support dashboards. | C6: Each shows its own numbers and charts. | D6: Pass
A7: 5 | B7: Log in as users with different roles and open the dashboard. | C7: Each role sees only the data their permissions allow.
A8: 6 | B8: Check 'overdue' items on a dashboard against the actual records. | C8: Overdue = past the end date and not closed; the count matches the records. | D8: Pass
A9: B. REPORTS — EXPORT
A10: 7 | B10: Open the Reports screen. | C10: It shows only the exports your role and plan allow (may be empty for a limited user). | D10: Fail
A11: 8 | B11: Export a data set (e.g. Leads). | C11: A file downloads with the correct data. | D11: Fail
A12: 9 | B12: As a user WITHOUT export permission, try to export. | C12: Export is blocked or hidden.
A13: 10 | B13: On a plan without report export, try to export. | C13: Blocked with an upgrade message.
A14: C. IMPORT
A15: 11 | B15: Import a data set from a correctly formatted file. | C15: Valid rows import. | D15: Blocked
A16: 12 | B16: Import a file with some bad rows (missing required fields, wrong format). | C16: Bad rows are reported clearly; good rows still import; nothing is silently corrupted. | D16: Blocked
A17: 13 | B17: Import a file that is empty or wholly wrong format. | C17: Rejected with a clear message; no crash. | D17: Blocked
A18: 14 | B18: Export leads that include custom fields, then re-import the same file. | C18: The round-trip keeps the custom field values intact. | D18: Blocked

Sheet 18. Misc (Cross-Module)
A1: Sl No | B1: Action | C1: Expected Outcome | D1: Result | E1: Remarks
A2: A. MENU & MODULE ACCESS (VERY IMPORTANT)
A3: 1 | B3: Log in and look at the left-hand menu. | C3: It shows all the sections your role allows. It is NOT blank or nearly empty.
A4: 2 | B4: Compare the menu for an admin vs a limited user. | C4: The admin sees more; the limited user sees fewer; each only what their role allows.
A5: 3 | B5: As a limited user, type the address of a section you do NOT have (e.g. Billing). | C5: A clear 'no access' panel is shown, not the real screen and not a broken page.
A6: 4 | B6: Confirm each of the seven modules that your plan/role should show actually appears: CRM, Project, Helpdesk, LMS, Admin/Settings, plus Reports and Dashboard. | C6: Each expected module is reachable from the menu.
A7: B. END-TO-END MULTI-MODULE JOURNEY (the money chain)
A8: 5 | B8: Capture a lead from the website form -> it is auto-routed to an agent -> the agent adds a quotation -> accepts it. | C8: Each step flows into the next: the lead becomes a customer and a payment plan appears automatically.
A9: 6 | B9: Open the new customer and create a PROJECT for them, then a support TICKET for them. | C9: The project and ticket link back to the same customer; the customer 360 view shows all three.
A10: 7 | B10: Raise a support ticket for that customer and confirm its SLA deadline. | C10: The ticket deadline uses that customer's SLA — set earlier in the CRM.
A11: 8 | B11: Run a report/dashboard and confirm this journey's lead, deal value and customer all appear. | C11: The numbers reflect the end-to-end journey consistently.
A12: C. DATA SEPARATION BETWEEN COMPANIES (SECURITY)
A13: 9 | B13: Note the address/id of a record (e.g. a lead) in Company A; open it while in Company A. | C13: It opens for Company A.
A14: 10 | B14: Log in as a user of a DIFFERENT company (Company B) and paste that same record address/id. | C14: Company B is blocked from seeing Company A's record. No data leaks across companies.
A15: 11 | B15: Repeat the cross-company check for a customer, a project and a ticket. | C15: None of Company A's records are reachable from Company B.
A16: D. SCOPE ENFORCEMENT ACROSS MODULES (not just leads)
A17: 12 | B17: Give a user 'owned records only' and confirm it holds for Leads, Customers, Tasks and Tickets alike. | C17: The same visibility rule applies across every module, consistently.
A18: 13 | B18: As a view-only user on a module, find a hidden action's address (delete/edit) and trigger it directly. | C18: Refused on the server, not just hidden in the screen — for every module tested.
A19: E. CUSTOM FIELD FLOWING THROUGH FEATURES
A20: 14 | B20: Create a lead custom field -> use it in a routing rule -> use it in an automation condition -> show it as a list column -> export it. | C20: The same custom field works consistently in capture, routing, automation, lists and export.
A21: 15 | B21: Delete that custom field and check the routing rule and automation that used it. | C21: The rules that referenced it are flagged/invalidated, not silently broken. (Mark N/A for automations if that area is unavailable.)
A22: F. NOTIFICATIONS ACROSS MODULES
A23: 16 | B23: Do actions that notify people (assign a lead, comment on a project task, resolve a ticket) and check each recipient's bell. | C23: Each person receives the right in-app notification for their module event.
A24: 17 | B24: Turn OFF a channel (e.g. e-mail) at company level in notification settings. | C24: No one in the company gets that type of notification by that channel any more.
A25: 18 | B25: As a single user, change your own notification preference for one event. | C25: Your personal choice is respected within the company-level rules.
A26: 19 | B26: Pin a notification and snooze another. | C26: The pinned one stays on top; the snoozed one hides until its time.
A27: G. ENTITLEMENT (PLAN) GATING ACROSS MODULES
A28: 20 | B28: On a plan missing a feature, confirm every entry point to it is blocked (menu item, direct URL, and any button elsewhere that opens it). | C28: The feature is blocked everywhere consistently, with an upgrade prompt — no partial access.
A29: H. FILE UPLOADS EVERYWHERE
A30: 21 | B30: Upload a file just over 10 MB in several places (lead, task, note, project, ticket, payment record). | C30: Oversized files are refused with a clear message, consistently, in every place.
A31: 22 | B31: Upload a file with a very long name and unusual characters. | C31: It uploads and shows the name correctly, or is cleaned sensibly.
A32: I. SEARCH, EMPTY & LOADING STATES
A33: 23 | B33: Search for something that does not exist in several lists. | C33: A clear 'no results' message is shown, not a blank or broken screen.
A34: 24 | B34: Open a brand-new empty section (e.g. no leads yet). | C34: A friendly empty-state message is shown.
A35: 25 | B35: Open a heavy screen on a slow connection. | C35: A loading indicator shows; the screen does not appear frozen or broken.
A36: J. INPUT LIMITS & ODD INPUT (across forms)
A37: 26 | B37: Paste extremely long text into single-line boxes in several forms. | C37: The app limits or handles it; the layout does not break.
A38: 27 | B38: Enter special characters, emoji and non-English text in several forms. | C38: Saved and shown correctly across the app.
A39: 28 | B39: Enter letters in number boxes, negatives, and impossible dates (e.g. 31 Feb). | C39: Bad values are blocked with clear messages; no broken data is saved.
A40: 29 | B40: Submit a form twice quickly (double-click Save). | C40: Only one record is created; no duplicate.
A41: K. MONEY & CURRENCY
A42: 30 | B42: Create records in more than one currency, then open a dashboard total that mixes them. | C42: Confirm how mixed currencies behave; note if different currencies appear added together (there is no currency conversion).
A43: L. BROWSER, DEVICE, THEME & NAVIGATION
A44: 31 | B44: Open the app on a phone-sized and a tablet-sized screen. | C44: The layout adapts and stays usable; nothing important is cut off.
A45: 32 | B45: Open the app in two different browsers. | C45: It looks and works the same in both.
A46: 33 | B46: Switch between light and dark appearance (if available). | C46: Text stays readable and colours look correct in both.
A47: 34 | B47: Use browser Back/Forward in the middle of a multi-step flow. | C47: The app keeps a sensible state; it does not lose your place or show broken data.
A48: 35 | B48: Refresh the page (F5) mid-way through a long form. | C48: The app warns about unsaved changes or reloads cleanly; no crash.
A49: M. CONCURRENT USE & ERROR HANDLING
A50: 36 | B50: Open the same record in two tabs/users; edit and save in both. | C50: The clash is handled sensibly; one person's change is not silently lost without any sign.
A51: 37 | B51: Throughout testing, watch for raw/technical errors, blank white pages, or endless loaders. | C51: Errors always appear as friendly, clear messages; no raw errors or dead pages reach the user.
A52: 38 | B52: Turn off the internet briefly during an action, then restore it. | C52: A clear connection message is shown and the app recovers without losing your login or corrupting data.
